{
  "crawled_at": "2026-06-04T11:59:55",
  "source_url": "https://www.agoda.com/days-inn-by-wyndham-hampton-near-coliseum-convention-center/hotel/hampton-va-us.html?hotel=2455164&currency=VND&checkIn=2026-06-14&checkOut=2026-06-15&rooms=1&adults=2&children=0",
  "hotel_id": 2455164,
  "name": "Days Inn by Hampton Near Coliseum Convention Center",
  "property_type": "Hotel",
  "accommodation_type": "Khách sạn",
  "star_rating": 2.0,
  "is_luxury": false,
  "gold_circle_award_year": null,
  "review_score": 7.5,
  "review_count": 515,
  "address": "1918 Coliseum Drive, Trung Tâm Mercury, Hampton (VA), Hoa Kỳ",
  "area": "Trung Tâm Mercury",
  "city": "Hampton (VA)",
  "country": "Hoa Kỳ",
  "postal_code": "23666",
  "latitude": 37.0399703979492,
  "longitude": -76.3867874145508,
  "description": "Phù hợp cho cả những chuyến công tác và du lịch nghỉ mát, Days Inn by Wyndham Hampton Near Coliseum Conventi nằm ở một vị trí lý tưởng tại Trung Tâm Mercury, một trong những địa điểm ruột của người dân bản địa. Từ đây, thật dễ dàng để trải nghiệm mọi khía cạnh của thành phố sống động này. Chỗ nghỉ có vị trí rất thuận tiện, du khách có thể thoải mái tham quan, khám phá các điểm du lịch nổi tiếng.\n\n Wyndham Hotels & Resorts nổi tiếng về chất lượng phục vụ cùng đội ngũ nhân viên thân thiện và Days Inn by Wyndham Hampton Near Coliseum Conventi thật đúng như mong đợi. Các tiện nghi như ăn sáng miễn phí luôn sẵn sàng phục vụ quý khách.\n\n Mọi phòng nghỉ đều được trang bị tiện nghi chu đáo, mang đến cho du khách cảm giác thoải mái không gì sánh được. Chỗ nghỉ cũng có nhiều phương tiện vui chơi giải trí để cho bạn không bao giờ cảm thấy nhàm chán. Cơ sở vật chất tuyệt vời và vị trí đắc địa làm cho Days Inn by Wyndham Hampton Near Coliseum Conventi trở thành điểm dừng hoàn hảo để bạn tận hưởng kỳ nghỉ ở Hampton (VA).",
  "check_in_from": "15:00",
  "check_out_until": "11:00",
  "year_built": null,
  "number_of_floors": null,
  "number_of_rooms": "144",
  "useful_info": {
    "Nhận phòng từ": "15:00",
    "Trả phòng đến": "11:00",
    "Số lượng phòng": "144"
  },
  "highlights": [
    "Wi-Fi miễn phí trong tất cả các phòng!",
    "Rút tiền mặt",
    "Điều hòa",
    "Nhận/trả phòng [nhanh]",
    "Thang máy"
  ],
  "location_tags": [
    "Bàn tiếp tân [24 giờ]",
    "Nhận/trả phòng [nhanh]",
    "Rút tiền mặt",
    "Wi-Fi miễn phí trong tất cả các phòng!",
    "Điều hòa"
  ],
  "amenities": [
    "Bàn tiếp tân 24 giờ",
    "Bể bơi trong nhà",
    "CCTV bên ngoài chỗ nghỉ",
    "CCTV trong khu vực chung",
    "Cơ sở vật chất cho họp mặt tiệc lớn",
    "Dịch vụ giặt là",
    "Dịch vụ ủi đồ",
    "Giãn cách vật lý ít nhất 1 mét",
    "Hành lang ngoài",
    "Không được bỏ mặc thú cưng",
    "Khử trùng hằng ngày",
    "Lò vi sóng",
    "Màn bảo vệ ở khu vực chung",
    "Máy bán hàng tự động",
    "Nhân viên đeo khẩu trang",
    "Nhận trả phòng nhanh",
    "Phòng không hút thuốc",
    "Phù hợp cho xe lăn",
    "Quán cà phê",
    "Rút tiền mặt",
    "Sàn gỗ miếng",
    "Sân gôn",
    "Sưởi",
    "Thang máy",
    "Tiếng Anh",
    "Tiện nghi cho khách khuyết tật",
    "Tủ lạnh",
    "WiFi miễn phí",
    "Điều hòa",
    "Đỗ xe miễn phí",
    "Đỗ xe tại chỗ",
    "Động vật hỗ trợ được chào đón"
  ],
  "amenities_count": 49,
  "amenity_groups": {
    "Ngôn ngữ được sử dụng": [
      "Tiếng Anh"
    ],
    "Khả năng tiếp cận cho người khuyết tật": [
      "Phù hợp cho xe lăn"
    ],
    "Truy cập Internet": [
      "WiFi miễn phí"
    ],
    "Thư giãn & Vui chơi giải trí": [
      "Bể bơi trong nhà"
    ],
    "Độ sạch sẽ và an toàn": [
      "Giãn cách vật lý ít nhất 1 mét",
      "Khử trùng hằng ngày",
      "Màn bảo vệ ở khu vực chung",
      "Nhân viên đeo khẩu trang"
    ],
    "Ăn uống": [
      "Máy bán hàng tự động",
      "Quán cà phê"
    ],
    "Dịch vụ và tiện nghi": [
      "Cơ sở vật chất cho họp mặt tiệc lớn",
      "Dịch vụ giặt là",
      "Dịch vụ ủi đồ",
      "Rút tiền mặt",
      "Thang máy",
      "Tiện nghi cho khách khuyết tật"
    ],
    "Hoạt động thể thao trên cạn ": [
      "Sân gôn"
    ],
    "Dễ dàng tiếp cận": [
      "Bàn tiếp tân 24 giờ",
      "CCTV bên ngoài chỗ nghỉ",
      "CCTV trong khu vực chung",
      "Hành lang ngoài",
      "Không được bỏ mặc thú cưng",
      "Nhận trả phòng nhanh",
      "Phòng không hút thuốc",
      "Động vật hỗ trợ được chào đón"
    ],
    "Đi lại": [
      "Đỗ xe miễn phí",
      "Đỗ xe tại chỗ"
    ],
    "Có trong tất cả phòng": [
      "Lò vi sóng",
      "Sàn gỗ miếng",
      "Sưởi",
      "Tủ lạnh",
      "Điều hòa"
    ]
  },
  "amenities_general": [
    "Bàn tiếp tân 24 giờ",
    "CCTV bên ngoài chỗ nghỉ",
    "CCTV trong khu vực chung",
    "Cơ sở vật chất cho họp mặt tiệc lớn",
    "Dịch vụ giặt là",
    "Dịch vụ ủi đồ",
    "Giãn cách vật lý ít nhất 1 mét",
    "Hành lang ngoài",
    "Không được bỏ mặc thú cưng",
    "Khử trùng hằng ngày",
    "Lò vi sóng",
    "Màn bảo vệ ở khu vực chung",
    "Nhân viên đeo khẩu trang",
    "Nhận trả phòng nhanh",
    "Phòng không hút thuốc",
    "Phù hợp cho xe lăn",
    "Rút tiền mặt",
    "Sàn gỗ miếng",
    "Sưởi",
    "Thang máy",
    "Tiếng Anh",
    "Tiện nghi cho khách khuyết tật",
    "Tủ lạnh",
    "WiFi miễn phí",
    "Điều hòa",
    "Đỗ xe miễn phí",
    "Đỗ xe tại chỗ",
    "Động vật hỗ trợ được chào đón"
  ],
  "amenities_leisure": [
    "Bể bơi trong nhà",
    "Sân gôn"
  ],
  "amenities_dining": [
    "Máy bán hàng tự động",
    "Quán cà phê"
  ],
  "nearby_places": [
    {
      "name": "Hampton Roads Convention Center",
      "type": "Cao Ốc Văn Phòng",
      "distance_km": 0.52
    },
    {
      "name": "Bluebird Gap Farm",
      "type": "Đài Kỷ Niệm và Di Tích Lịch Sử",
      "distance_km": 0.58
    },
    {
      "name": "Green Gates Gifts",
      "type": "Trung Tâm và Khu Mua Sắm",
      "distance_km": 0.7
    },
    {
      "name": "Hampton Coliseum",
      "type": "Các Sân Thể Thao",
      "distance_km": 0.72
    },
    {
      "name": "Air Power Park",
      "type": "Viện Bảo Tàng và Phòng Trưng Bày Nghệ Thuật",
      "distance_km": 1.86
    },
    {
      "name": "Hampton Air Power Park & Museum",
      "type": "Viện Bảo Tàng và Phòng Trưng Bày Nghệ Thuật",
      "distance_km": 1.93
    },
    {
      "name": "Boo Williams Sportplex",
      "type": "Các Sân Thể Thao",
      "distance_km": 2.22
    },
    {
      "name": "War Memorial Stadium",
      "type": "Các Sân Thể Thao",
      "distance_km": 3.38
    },
    {
      "name": "Traiding Golf Course",
      "type": "Sân Gôn",
      "distance_km": 3.81
    },
    {
      "name": "Langley AFB",
      "type": "Cao Ốc Văn Phòng",
      "distance_km": 3.85
    }
  ],
  "image_count": 15,
  "image_urls": [
    "https://pix8.agoda.net/hotelImages/2455164/-1/429984dc681a5537980c913b63f64172.jpg?ca=13&ce=1&s=1024x768",
    "https://pix8.agoda.net/hotelImages/2455164/-1/3dea09c0edbe567b513d45325f1182b6.jpg?ca=13&ce=1&s=1024x768",
    "https://pix8.agoda.net/hotelImages/2455164/-1/f50aa41dbbf9cd0666f00f343165453a.jpg?ca=13&ce=1&s=1024x768",
    "https://pix8.agoda.net/hotelImages/2455164/-1/30e0177db16fcb8f31cf49cdab134dc6.jpg?ca=13&ce=1&s=1024x768",
    "https://pix8.agoda.net/hotelImages/245/2455164/2455164_18032912540063100068.jpg?ca=6&ce=1&s=1024x768",
    "https://pix8.agoda.net/hotelImages/2455164/-1/e471629b3f30c4ad29f93e50e3d7cab9.jpg?ca=13&ce=1&s=1024x768",
    "https://pix8.agoda.net/hotelImages/2455164/-1/5ec50c24a4d5f970941fd5e9f3391d55.jpg?ca=13&ce=1&s=1024x768",
    "https://pix8.agoda.net/hotelImages/2455164/-1/239f389b1004f8e8ae815efa54a3b558.jpg?ca=13&ce=1&s=1024x768",
    "https://pix8.agoda.net/hotelImages/2455164/-1/cd1ba196f6878a35912c41b693db1630.jpg?ca=13&ce=1&s=1024x768",
    "https://pix8.agoda.net/hotelImages/2455164/-1/2eab45e4f020394380a7a9c4c45ec8d0.jpg?ca=13&ce=1&s=1024x768",
    "https://pix8.agoda.net/hotelImages/2455164/-1/1cbf6f3887c0ead76dcd2f7134bce713.jpg?ca=13&ce=1&s=1024x768",
    "https://pix8.agoda.net/hotelImages/2455164/-1/500595083df0d552aabcc66efa379f19.jpg?ca=13&ce=1&s=1024x768",
    "https://pix8.agoda.net/hotelImages/2455164/-1/4b9e410471eac9fa1b4a61aa41b82aff.jpg?ca=13&ce=1&s=1024x768",
    "https://pix8.agoda.net/hotelImages/2455164/-1/eb1a4b4e5c01ab9779b3ec62524d4008.jpg?ca=13&ce=1&s=1024x768",
    "https://pix8.agoda.net/hotelImages/2455164/32191141/cab1226f2cfd9ede5919662f0daebf7d.jpeg?ce=0&s=1024x768"
  ],
  "images": [
    {
      "url": "https://pix8.agoda.net/hotelImages/2455164/-1/429984dc681a5537980c913b63f64172.jpg?ca=13&ce=1&s=1024x768",
      "caption": "Hành lang",
      "category": "Khách sạn"
    },
    {
      "url": "https://pix8.agoda.net/hotelImages/2455164/-1/3dea09c0edbe567b513d45325f1182b6.jpg?ca=13&ce=1&s=1024x768",
      "caption": "Phòng có giường King - Phù hợp cho người khuyết tật, không hút thuốc - Cảnh quan",
      "category": "Phòng"
    },
    {
      "url": "https://pix8.agoda.net/hotelImages/2455164/-1/f50aa41dbbf9cd0666f00f343165453a.jpg?ca=13&ce=1&s=1024x768",
      "caption": "Ngoại cảnh khách sạn",
      "category": "Khách sạn"
    },
    {
      "url": "https://pix8.agoda.net/hotelImages/2455164/-1/30e0177db16fcb8f31cf49cdab134dc6.jpg?ca=13&ce=1&s=1024x768",
      "caption": "Đồ ăn và thức uống",
      "category": "Ăn uống"
    },
    {
      "url": "https://pix8.agoda.net/hotelImages/245/2455164/2455164_18032912540063100068.jpg?ca=6&ce=1&s=1024x768",
      "caption": "Ngoại cảnh khách sạn",
      "category": "Khách sạn"
    },
    {
      "url": "https://pix8.agoda.net/hotelImages/2455164/-1/e471629b3f30c4ad29f93e50e3d7cab9.jpg?ca=13&ce=1&s=1024x768",
      "caption": "Ngoại cảnh khách sạn",
      "category": "Khách sạn"
    },
    {
      "url": "https://pix8.agoda.net/hotelImages/2455164/-1/5ec50c24a4d5f970941fd5e9f3391d55.jpg?ca=13&ce=1&s=1024x768",
      "caption": "Ngoại cảnh khách sạn",
      "category": "Khách sạn"
    },
    {
      "url": "https://pix8.agoda.net/hotelImages/2455164/-1/239f389b1004f8e8ae815efa54a3b558.jpg?ca=13&ce=1&s=1024x768",
      "caption": "Two Double Beds Non-Smoking - Phòng ốc",
      "category": "Phòng"
    },
    {
      "url": "https://pix8.agoda.net/hotelImages/2455164/-1/cd1ba196f6878a35912c41b693db1630.jpg?ca=13&ce=1&s=1024x768",
      "caption": "Đồ ăn và thức uống",
      "category": "Ăn uống"
    },
    {
      "url": "https://pix8.agoda.net/hotelImages/2455164/-1/2eab45e4f020394380a7a9c4c45ec8d0.jpg?ca=13&ce=1&s=1024x768",
      "caption": "Quán Cà phê",
      "category": "Ăn uống"
    },
    {
      "url": "https://pix8.agoda.net/hotelImages/2455164/-1/1cbf6f3887c0ead76dcd2f7134bce713.jpg?ca=13&ce=1&s=1024x768",
      "caption": "1 King Bed Smoking - Giường",
      "category": "Phòng"
    },
    {
      "url": "https://pix8.agoda.net/hotelImages/2455164/-1/500595083df0d552aabcc66efa379f19.jpg?ca=13&ce=1&s=1024x768",
      "caption": "Cơ sở vật chất",
      "category": "Cơ sở vật chất"
    },
    {
      "url": "https://pix8.agoda.net/hotelImages/2455164/-1/4b9e410471eac9fa1b4a61aa41b82aff.jpg?ca=13&ce=1&s=1024x768",
      "caption": "1 King Bed Smoking - Phòng ốc",
      "category": "Phòng"
    },
    {
      "url": "https://pix8.agoda.net/hotelImages/2455164/-1/eb1a4b4e5c01ab9779b3ec62524d4008.jpg?ca=13&ce=1&s=1024x768",
      "caption": "Two Double Beds Non-Smoking - Giường",
      "category": "Phòng"
    },
    {
      "url": "https://pix8.agoda.net/hotelImages/2455164/32191141/cab1226f2cfd9ede5919662f0daebf7d.jpeg?ce=0&s=1024x768",
      "caption": "Phòng có giường King - Phù hợp cho người khuyết tật, không hút thuốc - Phòng ốc",
      "category": "Phòng"
    }
  ],
  "district": "Trung Tâm Mercury",
  "province": "Hampton (VA)",
  "city_id": 5014,
  "property_page": "/days-inn-by-wyndham-hampton-near-coliseum-convention-center/hotel/hampton-va-us.html",
  "room_grid": {
    "is_sold_out": false,
    "cheapest_price": null,
    "room_count": 6,
    "rooms": [
      {
        "room_type_id": 32191145,
        "name": "Two Double Beds Non-Smoking",
        "name_en": null,
        "room_size": null,
        "size_sqm": null,
        "max_occupancy": 4,
        "max_occupancy_text": "Tối đa 4 người lớn",
        "bed_type": "2 giường đôi",
        "bed_types": [
          "2 giường đôi"
        ],
        "room_view": null,
        "is_sold_out": false,
        "facilities": [
          "Không hút thuốc",
          "Vòi sen"
        ],
        "room_amenities": [
          "2 giường đôi",
          "Bố trí và nội thất phòng",
          "Giải trí",
          "Không hút thuốc",
          "Lò vi sóng",
          "Phòng tắm và vật dụng vệ sinh",
          "Quần áo và giặt ủi",
          "Sàn gỗ miếng",
          "Sưởi",
          "TV",
          "Tính năng an toàn và an ninh",
          "Tủ lạnh",
          "Ăn uống",
          "Điều hòa"
        ],
        "image_count": 4,
        "images": [
          "https://pix8.agoda.net/hotelImages/2455164/-1/239f389b1004f8e8ae815efa54a3b558.jpg?ca=13&ce=1&s=800x600",
          "https://pix8.agoda.net/hotelImages/2455164/-1/eb1a4b4e5c01ab9779b3ec62524d4008.jpg?ca=13&ce=1&s=800x600",
          "https://pix8.agoda.net/hotelImages/2455164/-1/c286d7961224a5951fa2f15a57c3fb6c.jpg?ca=13&ce=1&s=800x600",
          "https://pix8.agoda.net/hotelImages/2455164/-1/5b9f273358fe8cac8a64f03604a3603c.jpg?ca=7&ce=1&s=800x600"
        ],
        "review_score": null,
        "price_per_night": 440000,
        "original_price": 550000
      },
      {
        "room_type_id": 32191146,
        "name": "1 King Bed Smoking",
        "name_en": null,
        "room_size": null,
        "size_sqm": null,
        "max_occupancy": 2,
        "max_occupancy_text": "Tối đa 2 người lớn",
        "bed_type": "1 giường lớn",
        "bed_types": [
          "1 giường lớn"
        ],
        "room_view": null,
        "is_sold_out": false,
        "facilities": [
          "Cho phép hút thuốc",
          "Vòi sen"
        ],
        "room_amenities": [
          "1 giường lớn",
          "Bố trí và nội thất phòng",
          "Cho phép hút thuốc",
          "Giải trí",
          "Lò vi sóng",
          "Máy pha trà cà phê",
          "Phòng tắm và vật dụng vệ sinh",
          "Quần áo và giặt ủi",
          "Sàn gỗ miếng",
          "Sưởi",
          "TV màn hình phẳng",
          "Tính năng an toàn và an ninh",
          "Tủ lạnh",
          "Ăn uống",
          "Điều hòa"
        ],
        "image_count": 4,
        "images": [
          "https://pix8.agoda.net/hotelImages/2455164/-1/3dea09c0edbe567b513d45325f1182b6.jpg?ca=13&ce=1&s=800x600",
          "https://pix8.agoda.net/hotelImages/2455164/-1/1cbf6f3887c0ead76dcd2f7134bce713.jpg?ca=13&ce=1&s=800x600",
          "https://pix8.agoda.net/hotelImages/2455164/-1/c286d7961224a5951fa2f15a57c3fb6c.jpg?ca=13&ce=1&s=800x600",
          "https://pix8.agoda.net/hotelImages/2455164/-1/4b9e410471eac9fa1b4a61aa41b82aff.jpg?ca=13&ce=1&s=800x600"
        ],
        "review_score": null,
        "price_per_night": 440000,
        "original_price": 630000
      },
      {
        "room_type_id": 77681683,
        "name": "Phòng có Giường Lớn và Phòng Tắm Có Lối Đi Thoai Thoải - Phù Hợp cho Người Khó Đi Lại, Không Hút Thuốc (1 King Bed, Mobility Accessible Room, Roll-In Shower, Non-Smoking)",
        "name_en": "(1 King Bed, Mobility Accessible Room, Roll-In Shower, Non-Smoking)",
        "room_size": null,
        "size_sqm": null,
        "max_occupancy": 2,
        "max_occupancy_text": "Tối đa 2 người lớn",
        "bed_type": "1 giường lớn",
        "bed_types": [
          "1 giường lớn"
        ],
        "room_view": null,
        "is_sold_out": false,
        "facilities": [
          "Không hút thuốc",
          "Vòi sen"
        ],
        "room_amenities": [
          "1 giường lớn",
          "Bố trí và nội thất phòng",
          "Giải trí",
          "Không hút thuốc",
          "Khả năng tiếp cận cho người khuyết tật",
          "Lò vi sóng",
          "Phòng tắm có lối đi thoai thoải",
          "Phòng tắm và vật dụng vệ sinh",
          "Quần áo và giặt ủi",
          "Sàn gỗ miếng",
          "Sưởi",
          "TV",
          "Tính năng an toàn và an ninh",
          "Tủ lạnh",
          "Ăn uống",
          "Điều hòa"
        ],
        "image_count": 4,
        "images": [
          "https://pix8.agoda.net/hotelImages/2455164/-1/3dea09c0edbe567b513d45325f1182b6.jpg?ca=13&ce=1&s=800x600",
          "https://pix8.agoda.net/hotelImages/2455164/32191141/cab1226f2cfd9ede5919662f0daebf7d.jpeg?ce=0&s=800x600",
          "https://pix8.agoda.net/hotelImages/2455164/-1/df62159bf27c1ee8d1a8a1fbb36c8567.jpg?ca=13&ce=1&s=800x600",
          "https://pix8.agoda.net/hotelImages/2455164/32191141/0dc29072ecdf1a5fba7102af7a17c50f.jpeg?ce=0&s=800x600"
        ],
        "review_score": null,
        "price_per_night": 440000,
        "original_price": 750000
      },
      {
        "room_type_id": 32191148,
        "name": "Two Double Beds Smoking",
        "name_en": null,
        "room_size": null,
        "size_sqm": null,
        "max_occupancy": 4,
        "max_occupancy_text": "Tối đa 4 người lớn",
        "bed_type": "2 giường đôi",
        "bed_types": [
          "2 giường đôi"
        ],
        "room_view": null,
        "is_sold_out": false,
        "facilities": [
          "Cho phép hút thuốc",
          "Vòi sen"
        ],
        "room_amenities": [
          "2 giường đôi",
          "Bố trí và nội thất phòng",
          "Cho phép hút thuốc",
          "Giải trí",
          "Lò vi sóng",
          "Phòng tắm và vật dụng vệ sinh",
          "Quần áo và giặt ủi",
          "Sàn gỗ miếng",
          "Sưởi",
          "TV",
          "Tính năng an toàn và an ninh",
          "Tủ lạnh",
          "Ăn uống",
          "Điều hòa"
        ],
        "image_count": 4,
        "images": [
          "https://pix8.agoda.net/hotelImages/2455164/-1/239f389b1004f8e8ae815efa54a3b558.jpg?ca=13&ce=1&s=800x600",
          "https://pix8.agoda.net/hotelImages/2455164/-1/eb1a4b4e5c01ab9779b3ec62524d4008.jpg?ca=13&ce=1&s=800x600",
          "https://pix8.agoda.net/hotelImages/2455164/-1/c286d7961224a5951fa2f15a57c3fb6c.jpg?ca=13&ce=1&s=800x600",
          "https://pix8.agoda.net/hotelImages/2455164/-1/5b9f273358fe8cac8a64f03604a3603c.jpg?ca=7&ce=1&s=800x600"
        ],
        "review_score": null,
        "price_per_night": 440000,
        "original_price": 570000
      },
      {
        "room_type_id": 32191141,
        "name": "Phòng có giường King - Phù hợp cho người khuyết tật, không hút thuốc (1 King Bed Accessible Non-Smoking)",
        "name_en": "(1 King Bed Accessible Non-Smoking)",
        "room_size": null,
        "size_sqm": null,
        "max_occupancy": 2,
        "max_occupancy_text": "Tối đa 2 người lớn",
        "bed_type": "1 giường lớn",
        "bed_types": [
          "1 giường lớn"
        ],
        "room_view": null,
        "is_sold_out": false,
        "facilities": [
          "Không hút thuốc",
          "Vòi sen"
        ],
        "room_amenities": [
          "1 giường lớn",
          "Bố trí và nội thất phòng",
          "Giải trí",
          "Không hút thuốc",
          "Lò vi sóng",
          "Phòng tắm và vật dụng vệ sinh",
          "Quần áo và giặt ủi",
          "Sàn gỗ miếng",
          "Sưởi",
          "TV",
          "Tính năng an toàn và an ninh",
          "Tủ lạnh",
          "Ăn uống",
          "Điều hòa"
        ],
        "image_count": 4,
        "images": [
          "https://pix8.agoda.net/hotelImages/2455164/-1/3dea09c0edbe567b513d45325f1182b6.jpg?ca=13&ce=1&s=800x600",
          "https://pix8.agoda.net/hotelImages/2455164/32191141/cab1226f2cfd9ede5919662f0daebf7d.jpeg?ce=0&s=800x600",
          "https://pix8.agoda.net/hotelImages/2455164/-1/7f5773cde39ee39858045da84237c154.jpg?ca=13&ce=1&s=800x600",
          "https://pix8.agoda.net/hotelImages/2455164/32191141/0dc29072ecdf1a5fba7102af7a17c50f.jpeg?ce=0&s=800x600"
        ],
        "review_score": 9.511,
        "price_per_night": 440000,
        "original_price": 770000
      },
      {
        "room_type_id": 32191149,
        "name": "Phòng có giường King - Không hút thuốc (One King Bed Non Smoking)",
        "name_en": "(One King Bed Non Smoking)",
        "room_size": null,
        "size_sqm": null,
        "max_occupancy": 2,
        "max_occupancy_text": "Tối đa 2 người lớn",
        "bed_type": "1 giường lớn",
        "bed_types": [
          "1 giường lớn"
        ],
        "room_view": null,
        "is_sold_out": false,
        "facilities": [
          "Không hút thuốc",
          "Vòi sen"
        ],
        "room_amenities": [
          "1 giường lớn",
          "Bố trí và nội thất phòng",
          "Giải trí",
          "Không hút thuốc",
          "Lò vi sóng",
          "Phòng tắm và vật dụng vệ sinh",
          "Quần áo và giặt ủi",
          "Sàn gỗ miếng",
          "Sưởi",
          "TV",
          "Tính năng an toàn và an ninh",
          "Tủ lạnh",
          "Ăn uống",
          "Điều hòa"
        ],
        "image_count": 4,
        "images": [
          "https://pix8.agoda.net/hotelImages/2455164/-1/3dea09c0edbe567b513d45325f1182b6.jpg?ca=13&ce=1&s=800x600",
          "https://pix8.agoda.net/hotelImages/2455164/-1/1cbf6f3887c0ead76dcd2f7134bce713.jpg?ca=13&ce=1&s=800x600",
          "https://pix8.agoda.net/hotelImages/2455164/-1/c286d7961224a5951fa2f15a57c3fb6c.jpg?ca=13&ce=1&s=800x600",
          "https://pix8.agoda.net/hotelImages/2455164/-1/4b9e410471eac9fa1b4a61aa41b82aff.jpg?ca=13&ce=1&s=800x600"
        ],
        "review_score": 8.1,
        "price_per_night": 440000,
        "original_price": 700000
      }
    ]
  },
  "rooms": [
    {
      "room_type_id": 32191145,
      "name": "Two Double Beds Non-Smoking",
      "name_en": null,
      "room_size": null,
      "size_sqm": null,
      "max_occupancy": 4,
      "max_occupancy_text": "Tối đa 4 người lớn",
      "bed_type": "2 giường đôi",
      "bed_types": [
        "2 giường đôi"
      ],
      "room_view": null,
      "is_sold_out": false,
      "facilities": [
        "Không hút thuốc",
        "Vòi sen"
      ],
      "room_amenities": [
        "2 giường đôi",
        "Bố trí và nội thất phòng",
        "Giải trí",
        "Không hút thuốc",
        "Lò vi sóng",
        "Phòng tắm và vật dụng vệ sinh",
        "Quần áo và giặt ủi",
        "Sàn gỗ miếng",
        "Sưởi",
        "TV",
        "Tính năng an toàn và an ninh",
        "Tủ lạnh",
        "Ăn uống",
        "Điều hòa"
      ],
      "image_count": 4,
      "images": [
        "https://pix8.agoda.net/hotelImages/2455164/-1/239f389b1004f8e8ae815efa54a3b558.jpg?ca=13&ce=1&s=800x600",
        "https://pix8.agoda.net/hotelImages/2455164/-1/eb1a4b4e5c01ab9779b3ec62524d4008.jpg?ca=13&ce=1&s=800x600",
        "https://pix8.agoda.net/hotelImages/2455164/-1/c286d7961224a5951fa2f15a57c3fb6c.jpg?ca=13&ce=1&s=800x600",
        "https://pix8.agoda.net/hotelImages/2455164/-1/5b9f273358fe8cac8a64f03604a3603c.jpg?ca=7&ce=1&s=800x600"
      ],
      "review_score": null,
      "price_per_night": 440000,
      "original_price": 550000
    },
    {
      "room_type_id": 32191146,
      "name": "1 King Bed Smoking",
      "name_en": null,
      "room_size": null,
      "size_sqm": null,
      "max_occupancy": 2,
      "max_occupancy_text": "Tối đa 2 người lớn",
      "bed_type": "1 giường lớn",
      "bed_types": [
        "1 giường lớn"
      ],
      "room_view": null,
      "is_sold_out": false,
      "facilities": [
        "Cho phép hút thuốc",
        "Vòi sen"
      ],
      "room_amenities": [
        "1 giường lớn",
        "Bố trí và nội thất phòng",
        "Cho phép hút thuốc",
        "Giải trí",
        "Lò vi sóng",
        "Máy pha trà cà phê",
        "Phòng tắm và vật dụng vệ sinh",
        "Quần áo và giặt ủi",
        "Sàn gỗ miếng",
        "Sưởi",
        "TV màn hình phẳng",
        "Tính năng an toàn và an ninh",
        "Tủ lạnh",
        "Ăn uống",
        "Điều hòa"
      ],
      "image_count": 4,
      "images": [
        "https://pix8.agoda.net/hotelImages/2455164/-1/3dea09c0edbe567b513d45325f1182b6.jpg?ca=13&ce=1&s=800x600",
        "https://pix8.agoda.net/hotelImages/2455164/-1/1cbf6f3887c0ead76dcd2f7134bce713.jpg?ca=13&ce=1&s=800x600",
        "https://pix8.agoda.net/hotelImages/2455164/-1/c286d7961224a5951fa2f15a57c3fb6c.jpg?ca=13&ce=1&s=800x600",
        "https://pix8.agoda.net/hotelImages/2455164/-1/4b9e410471eac9fa1b4a61aa41b82aff.jpg?ca=13&ce=1&s=800x600"
      ],
      "review_score": null,
      "price_per_night": 440000,
      "original_price": 630000
    },
    {
      "room_type_id": 77681683,
      "name": "Phòng có Giường Lớn và Phòng Tắm Có Lối Đi Thoai Thoải - Phù Hợp cho Người Khó Đi Lại, Không Hút Thuốc (1 King Bed, Mobility Accessible Room, Roll-In Shower, Non-Smoking)",
      "name_en": "(1 King Bed, Mobility Accessible Room, Roll-In Shower, Non-Smoking)",
      "room_size": null,
      "size_sqm": null,
      "max_occupancy": 2,
      "max_occupancy_text": "Tối đa 2 người lớn",
      "bed_type": "1 giường lớn",
      "bed_types": [
        "1 giường lớn"
      ],
      "room_view": null,
      "is_sold_out": false,
      "facilities": [
        "Không hút thuốc",
        "Vòi sen"
      ],
      "room_amenities": [
        "1 giường lớn",
        "Bố trí và nội thất phòng",
        "Giải trí",
        "Không hút thuốc",
        "Khả năng tiếp cận cho người khuyết tật",
        "Lò vi sóng",
        "Phòng tắm có lối đi thoai thoải",
        "Phòng tắm và vật dụng vệ sinh",
        "Quần áo và giặt ủi",
        "Sàn gỗ miếng",
        "Sưởi",
        "TV",
        "Tính năng an toàn và an ninh",
        "Tủ lạnh",
        "Ăn uống",
        "Điều hòa"
      ],
      "image_count": 4,
      "images": [
        "https://pix8.agoda.net/hotelImages/2455164/-1/3dea09c0edbe567b513d45325f1182b6.jpg?ca=13&ce=1&s=800x600",
        "https://pix8.agoda.net/hotelImages/2455164/32191141/cab1226f2cfd9ede5919662f0daebf7d.jpeg?ce=0&s=800x600",
        "https://pix8.agoda.net/hotelImages/2455164/-1/df62159bf27c1ee8d1a8a1fbb36c8567.jpg?ca=13&ce=1&s=800x600",
        "https://pix8.agoda.net/hotelImages/2455164/32191141/0dc29072ecdf1a5fba7102af7a17c50f.jpeg?ce=0&s=800x600"
      ],
      "review_score": null,
      "price_per_night": 440000,
      "original_price": 750000
    },
    {
      "room_type_id": 32191148,
      "name": "Two Double Beds Smoking",
      "name_en": null,
      "room_size": null,
      "size_sqm": null,
      "max_occupancy": 4,
      "max_occupancy_text": "Tối đa 4 người lớn",
      "bed_type": "2 giường đôi",
      "bed_types": [
        "2 giường đôi"
      ],
      "room_view": null,
      "is_sold_out": false,
      "facilities": [
        "Cho phép hút thuốc",
        "Vòi sen"
      ],
      "room_amenities": [
        "2 giường đôi",
        "Bố trí và nội thất phòng",
        "Cho phép hút thuốc",
        "Giải trí",
        "Lò vi sóng",
        "Phòng tắm và vật dụng vệ sinh",
        "Quần áo và giặt ủi",
        "Sàn gỗ miếng",
        "Sưởi",
        "TV",
        "Tính năng an toàn và an ninh",
        "Tủ lạnh",
        "Ăn uống",
        "Điều hòa"
      ],
      "image_count": 4,
      "images": [
        "https://pix8.agoda.net/hotelImages/2455164/-1/239f389b1004f8e8ae815efa54a3b558.jpg?ca=13&ce=1&s=800x600",
        "https://pix8.agoda.net/hotelImages/2455164/-1/eb1a4b4e5c01ab9779b3ec62524d4008.jpg?ca=13&ce=1&s=800x600",
        "https://pix8.agoda.net/hotelImages/2455164/-1/c286d7961224a5951fa2f15a57c3fb6c.jpg?ca=13&ce=1&s=800x600",
        "https://pix8.agoda.net/hotelImages/2455164/-1/5b9f273358fe8cac8a64f03604a3603c.jpg?ca=7&ce=1&s=800x600"
      ],
      "review_score": null,
      "price_per_night": 440000,
      "original_price": 570000
    },
    {
      "room_type_id": 32191141,
      "name": "Phòng có giường King - Phù hợp cho người khuyết tật, không hút thuốc (1 King Bed Accessible Non-Smoking)",
      "name_en": "(1 King Bed Accessible Non-Smoking)",
      "room_size": null,
      "size_sqm": null,
      "max_occupancy": 2,
      "max_occupancy_text": "Tối đa 2 người lớn",
      "bed_type": "1 giường lớn",
      "bed_types": [
        "1 giường lớn"
      ],
      "room_view": null,
      "is_sold_out": false,
      "facilities": [
        "Không hút thuốc",
        "Vòi sen"
      ],
      "room_amenities": [
        "1 giường lớn",
        "Bố trí và nội thất phòng",
        "Giải trí",
        "Không hút thuốc",
        "Lò vi sóng",
        "Phòng tắm và vật dụng vệ sinh",
        "Quần áo và giặt ủi",
        "Sàn gỗ miếng",
        "Sưởi",
        "TV",
        "Tính năng an toàn và an ninh",
        "Tủ lạnh",
        "Ăn uống",
        "Điều hòa"
      ],
      "image_count": 4,
      "images": [
        "https://pix8.agoda.net/hotelImages/2455164/-1/3dea09c0edbe567b513d45325f1182b6.jpg?ca=13&ce=1&s=800x600",
        "https://pix8.agoda.net/hotelImages/2455164/32191141/cab1226f2cfd9ede5919662f0daebf7d.jpeg?ce=0&s=800x600",
        "https://pix8.agoda.net/hotelImages/2455164/-1/7f5773cde39ee39858045da84237c154.jpg?ca=13&ce=1&s=800x600",
        "https://pix8.agoda.net/hotelImages/2455164/32191141/0dc29072ecdf1a5fba7102af7a17c50f.jpeg?ce=0&s=800x600"
      ],
      "review_score": 9.511,
      "price_per_night": 440000,
      "original_price": 770000
    },
    {
      "room_type_id": 32191149,
      "name": "Phòng có giường King - Không hút thuốc (One King Bed Non Smoking)",
      "name_en": "(One King Bed Non Smoking)",
      "room_size": null,
      "size_sqm": null,
      "max_occupancy": 2,
      "max_occupancy_text": "Tối đa 2 người lớn",
      "bed_type": "1 giường lớn",
      "bed_types": [
        "1 giường lớn"
      ],
      "room_view": null,
      "is_sold_out": false,
      "facilities": [
        "Không hút thuốc",
        "Vòi sen"
      ],
      "room_amenities": [
        "1 giường lớn",
        "Bố trí và nội thất phòng",
        "Giải trí",
        "Không hút thuốc",
        "Lò vi sóng",
        "Phòng tắm và vật dụng vệ sinh",
        "Quần áo và giặt ủi",
        "Sàn gỗ miếng",
        "Sưởi",
        "TV",
        "Tính năng an toàn và an ninh",
        "Tủ lạnh",
        "Ăn uống",
        "Điều hòa"
      ],
      "image_count": 4,
      "images": [
        "https://pix8.agoda.net/hotelImages/2455164/-1/3dea09c0edbe567b513d45325f1182b6.jpg?ca=13&ce=1&s=800x600",
        "https://pix8.agoda.net/hotelImages/2455164/-1/1cbf6f3887c0ead76dcd2f7134bce713.jpg?ca=13&ce=1&s=800x600",
        "https://pix8.agoda.net/hotelImages/2455164/-1/c286d7961224a5951fa2f15a57c3fb6c.jpg?ca=13&ce=1&s=800x600",
        "https://pix8.agoda.net/hotelImages/2455164/-1/4b9e410471eac9fa1b4a61aa41b82aff.jpg?ca=13&ce=1&s=800x600"
      ],
      "review_score": 8.1,
      "price_per_night": 440000,
      "original_price": 700000
    }
  ],
  "reviews_detail": {
    "score": 7.5,
    "score_text": null,
    "review_count": 515,
    "comments_count": null,
    "grades": [
      {
        "name": "Độ sạch sẽ",
        "score": 7.1
      },
      {
        "name": "Cơ sở vật chất",
        "score": 7.1
      },
      {
        "name": "Vị trí",
        "score": 8.4
      },
      {
        "name": "Dịch vụ",
        "score": 7.6
      },
      {
        "name": "Đáng tiền",
        "score": 7.4
      }
    ],
    "tags": [
      {
        "tag": "Độ sạch sẽ",
        "mentioned": 19,
        "positive_pct": 21.0
      },
      {
        "tag": "Dịch vụ",
        "mentioned": 15,
        "positive_pct": 46.0
      },
      {
        "tag": "Địa điểm",
        "mentioned": 7,
        "positive_pct": 100.0
      },
      {
        "tag": "Bữa sáng",
        "mentioned": 6,
        "positive_pct": 0.0
      },
      {
        "tag": "Độ thoải mái của phòng",
        "mentioned": 6,
        "positive_pct": 33.0
      },
      {
        "tag": "Đáng tiền",
        "mentioned": 6,
        "positive_pct": 83.0
      },
      {
        "tag": "Bể bơi",
        "mentioned": 4,
        "positive_pct": 0.0
      },
      {
        "tag": "Vòi sen",
        "mentioned": 3,
        "positive_pct": 0.0
      },
      {
        "tag": "Cách âm",
        "mentioned": 3,
        "positive_pct": 0.0
      },
      {
        "tag": "Trả phòng",
        "mentioned": 2,
        "positive_pct": 0.0
      },
      {
        "tag": "Không khí",
        "mentioned": 2,
        "positive_pct": 0.0
      },
      {
        "tag": "Điều hòa",
        "mentioned": 1,
        "positive_pct": 0.0
      },
      {
        "tag": "Phòng tắm",
        "mentioned": 1,
        "positive_pct": 0.0
      },
      {
        "tag": "Nhận phòng",
        "mentioned": 1,
        "positive_pct": 0.0
      },
      {
        "tag": "Nước nóng",
        "mentioned": 1,
        "positive_pct": 0.0
      },
      {
        "tag": "Tiện ích tại cơ sở lưu trú",
        "mentioned": 1,
        "positive_pct": 100.0
      },
      {
        "tag": "Kích thước phòng",
        "mentioned": 1,
        "positive_pct": 0.0
      },
      {
        "tag": "An toàn",
        "mentioned": 1,
        "positive_pct": 0.0
      },
      {
        "tag": "Hoạt động không thể bỏ qua",
        "mentioned": 1,
        "positive_pct": 0.0
      },
      {
        "tag": "Thiết kế phòng",
        "mentioned": 1,
        "positive_pct": 0.0
      }
    ],
    "word_cloud": [],
    "demographics": [
      {
        "name": "Khách đi công tác",
        "count": 7,
        "score": 5.0
      },
      {
        "name": "Cặp đôi",
        "count": 227,
        "score": 7.8
      },
      {
        "name": "Khách du lịch một mình",
        "count": 107,
        "score": 7.7
      },
      {
        "name": "Gia đình có trẻ nhỏ",
        "count": 23,
        "score": 6.2
      },
      {
        "name": "Gia đình có thanh thiếu niên",
        "count": 13,
        "score": 5.5
      },
      {
        "name": "Nhóm du khách",
        "count": 24,
        "score": 7.7
      }
    ],
    "sample_comments": [
      {
        "rating": 10.0,
        "rating_text": "Trên cả tuyệt vời",
        "date": "06 tháng 6 2025",
        "check_in": "Tháng 6 năm 2025",
        "text": "Giá trị tuyệt vời, vị trí xuất sắc, nhân viên chuyên nghiệp và chu đáo; sạch sẽ và được bảo trì tốt.",
        "title": "Giá trị tuyệt vời",
        "positives": null,
        "negatives": null,
        "response": null,
        "reviewer_name": "Michael",
        "reviewer_type": "Du lịch một mình",
        "reviewer_country": "Hoa Kỳ",
        "room_type": "Phòng có giường King - Phù hợp cho người khuyết tật, không hút thuốc"
      },
      {
        "rating": 10.0,
        "rating_text": "Trên cả tuyệt vời",
        "date": "14 tháng 9 2025",
        "check_in": "",
        "text": null,
        "title": "Trên cả tuyệt vời",
        "positives": "Staff",
        "negatives": "No chain Locks",
        "response": null,
        "reviewer_name": "Tony",
        "reviewer_type": "Nhóm",
        "reviewer_country": "",
        "room_type": ""
      },
      {
        "rating": 10.0,
        "rating_text": "Trên cả tuyệt vời",
        "date": "23 tháng 4 2025",
        "check_in": "Tháng 4 năm 2025",
        "text": "Tôi đã ở đây nhiều lần. Đây là những người tốt làm việc chăm chỉ để đảm bảo khách có một kỳ nghỉ dễ chịu. Vị trí rất tuyệt vời. Các phòng nghỉ được chăm sóc kỹ lưỡng, đơn giản và sạch sẽ. Tôi khuyên bạn nên đến nơi này.",
        "title": "Nơi tuyệt vời để ở lại",
        "positives": null,
        "negatives": null,
        "response": null,
        "reviewer_name": "Michael",
        "reviewer_type": "Du lịch một mình",
        "reviewer_country": "Hoa Kỳ",
        "room_type": "Phòng có Giường Lớn và Phòng Tắm Có Lối Đi Thoai Thoải - Phù Hợp cho Người Khó Đi Lại, Không Hút Thuốc"
      },
      {
        "rating": 7.0,
        "rating_text": "Rất tốt",
        "date": "03 tháng 9 2025",
        "check_in": "",
        "text": "This guest did not leave comments about this hotel.",
        "title": "Rất tốt",
        "positives": null,
        "negatives": null,
        "response": null,
        "reviewer_name": "James",
        "reviewer_type": "Nhóm",
        "reviewer_country": "",
        "room_type": ""
      },
      {
        "rating": 10.0,
        "rating_text": "Trên cả tuyệt vời",
        "date": "16 tháng 4 2025",
        "check_in": "Tháng 4 năm 2025",
        "text": "Tôi thực sự đã có một khoảng thời gian tuyệt vời, nhân viên rất xuất sắc và họ đã làm cho tôi cảm thấy được chào đón.",
        "title": "Kinh nghiệm tốt",
        "positives": null,
        "negatives": null,
        "response": null,
        "reviewer_name": "Marcus",
        "reviewer_type": "Du lịch một mình",
        "reviewer_country": "Hoa Kỳ",
        "room_type": "Phòng có giường King - Không hút thuốc"
      },
      {
        "rating": 1.0,
        "rating_text": "Điểm nhận xét",
        "date": "26 tháng 8 2025",
        "check_in": "",
        "text": null,
        "title": "Chấp nhận được",
        "positives": "Price",
        "negatives": "Room condition",
        "response": null,
        "reviewer_name": "James",
        "reviewer_type": "Nhóm",
        "reviewer_country": "",
        "room_type": ""
      },
      {
        "rating": 9.2,
        "rating_text": "Trên cả tuyệt vời",
        "date": "17 tháng 5 2025",
        "check_in": "Tháng 5 năm 2025",
        "text": "Giá trị tuyệt vời, nhân viên hỗ trợ tuyệt vời, địa điểm nổi bật. Đây là nơi có giá cả phải chăng tại khu vực Coliseum!",
        "title": "Nhân viên xuất sắc và vị trí tuyệt vời.",
        "positives": null,
        "negatives": null,
        "response": null,
        "reviewer_name": "Michael",
        "reviewer_type": "Du lịch một mình",
        "reviewer_country": "Hoa Kỳ",
        "room_type": "Phòng có Giường Lớn và Phòng Tắm Có Lối Đi Thoai Thoải - Phù Hợp cho Người Khó Đi Lại, Không Hút Thuốc"
      },
      {
        "rating": 8.0,
        "rating_text": "Tuyệt vời",
        "date": "17 tháng 8 2025",
        "check_in": "",
        "text": "This guest did not leave comments about this hotel.",
        "title": "Rất tốt",
        "positives": null,
        "negatives": null,
        "response": null,
        "reviewer_name": "Bobby",
        "reviewer_type": "Nhóm",
        "reviewer_country": "",
        "room_type": ""
      },
      {
        "rating": 9.2,
        "rating_text": "Trên cả tuyệt vời",
        "date": "25 tháng 12 2025",
        "check_in": "Tháng 7 năm 2025",
        "text": "Điều tuyệt vời nhất về motel này là nó thân thiện với thú cưng, một thú cưng được miễn phí. Nhân viên dọn dẹp ở đó để giúp bạn với những nhu cầu trong thời gian lưu trú của bạn.",
        "title": "Theo cách thân thiện",
        "positives": null,
        "negatives": null,
        "response": null,
        "reviewer_name": "Velvet",
        "reviewer_type": "Du lịch một mình",
        "reviewer_country": "Hoa Kỳ",
        "room_type": "Two Double Beds Smoking"
      },
      {
        "rating": 10.0,
        "rating_text": "Trên cả tuyệt vời",
        "date": "16 tháng 8 2025",
        "check_in": "",
        "text": null,
        "title": "Trên cả tuyệt vời",
        "positives": "Glean comfortable bed's definitely also price",
        "negatives": "The water pressure was low",
        "response": null,
        "reviewer_name": "Alex",
        "reviewer_type": "Nhóm",
        "reviewer_country": "",
        "room_type": ""
      }
    ]
  },
  "rating_overall": 7.5,
  "rating_count": 515,
  "rating_breakdown": {
    "Độ sạch sẽ": 7.1,
    "Cơ sở vật chất": 7.1,
    "Vị trí": 8.4,
    "Dịch vụ": 7.6,
    "Đáng tiền": 7.4
  },
  "secondary": {
    "description_full": "Phù hợp cho cả những chuyến công tác và du lịch nghỉ mát, Days Inn by Wyndham Hampton Near Coliseum Conventi nằm ở một vị trí lý tưởng tại Trung Tâm Mercury, một trong những địa điểm ruột của người dân bản địa. Từ đây, thật dễ dàng để trải nghiệm mọi khía cạnh của thành phố sống động này. Chỗ nghỉ có vị trí rất thuận tiện, du khách có thể thoải mái tham quan, khám phá các điểm du lịch nổi tiếng.\n\n Wyndham Hotels & Resorts nổi tiếng về chất lượng phục vụ cùng đội ngũ nhân viên thân thiện và Days Inn by Wyndham Hampton Near Coliseum Conventi thật đúng như mong đợi. Các tiện nghi như ăn sáng miễn phí luôn sẵn sàng phục vụ quý khách.\n\n Mọi phòng nghỉ đều được trang bị tiện nghi chu đáo, mang đến cho du khách cảm giác thoải mái không gì sánh được. Chỗ nghỉ cũng có nhiều phương tiện vui chơi giải trí để cho bạn không bao giờ cảm thấy nhàm chán. Cơ sở vật chất tuyệt vời và vị trí đắc địa làm cho Days Inn by Wyndham Hampton Near Coliseum Conventi trở thành điểm dừng hoàn hảo để bạn tận hưởng kỳ nghỉ ở Hampton (VA).",
    "hotel_policy": {
      "childPolicies": [
        {
          "isInfant": false,
          "policy": "Trẻ em 0-1 tuổi [bao gồm cả bé 1 tuổi]",
          "description": "Ở miễn phí nếu sử dụng giường có sẵn."
        }
      ],
      "extrabedPolicies": [
        {
          "type": 1,
          "description": "Giường phụ tùy thuộc vào loại phòng bạn chọn, xin vui lòng kiểm tra thông tin phòng để biết thêm chi tiết."
        }
      ],
      "policyNotes": [
        "Bữa sáng ăn nhẹ miễn phí được phục vụ hàng ngày từ 6 giờ sáng đến 9 giờ sáng. (Nội dung này đã được máy dịch.)"
      ],
      "hideAutomatedChildPolicyText": false,
      "extraBedAge": 1,
      "hasBcomChildPolicy": false
    },
    "other_policies": [],
    "dateless_rooms_count": 6,
    "dateless_rooms": [
      {
        "room_id": 32191145,
        "name": "Two Double Beds Non-Smoking",
        "features": [],
        "image_count": 4,
        "bed_summary": {
          "symbol": "ficon-bed",
          "title": "2 giường đôi",
          "isAvailable": true,
          "id": 15,
          "value": 0.0,
          "associatedFilters": [
            "twin-bed",
            "double-bed"
          ],
          "targetType": 0,
          "hasDescription": false
        }
      },
      {
        "room_id": 32191146,
        "name": "1 King Bed Smoking",
        "features": [],
        "image_count": 4,
        "bed_summary": {
          "symbol": "ficon-bed",
          "title": "1 giường lớn",
          "isAvailable": true,
          "id": 15,
          "value": 0.0,
          "associatedFilters": [
            "twin-bed",
            "double-bed"
          ],
          "targetType": 0,
          "hasDescription": false
        }
      },
      {
        "room_id": 77681683,
        "name": "Phòng có Giường Lớn và Phòng Tắm Có Lối Đi Thoai Thoải - Phù Hợp cho Người Khó Đi Lại, Không Hút Thuốc (1 King Bed, Mobility Accessible Room, Roll-In Shower, Non-Smoking)",
        "features": [],
        "image_count": 4,
        "bed_summary": {
          "symbol": "ficon-bed",
          "title": "1 giường lớn",
          "isAvailable": true,
          "id": 15,
          "value": 0.0,
          "associatedFilters": [
            "twin-bed",
            "double-bed"
          ],
          "targetType": 0,
          "hasDescription": false
        }
      },
      {
        "room_id": 32191148,
        "name": "Two Double Beds Smoking",
        "features": [],
        "image_count": 4,
        "bed_summary": {
          "symbol": "ficon-bed",
          "title": "2 giường đôi",
          "isAvailable": true,
          "id": 15,
          "value": 0.0,
          "associatedFilters": [
            "twin-bed",
            "double-bed"
          ],
          "targetType": 0,
          "hasDescription": false
        }
      },
      {
        "room_id": 32191141,
        "name": "Phòng có giường King - Phù hợp cho người khuyết tật, không hút thuốc (1 King Bed Accessible Non-Smoking)",
        "features": [],
        "image_count": 4,
        "bed_summary": {
          "symbol": "ficon-bed",
          "title": "1 giường lớn",
          "isAvailable": true,
          "id": 15,
          "value": 0.0,
          "associatedFilters": [
            "twin-bed",
            "double-bed"
          ],
          "targetType": 0,
          "hasDescription": false
        }
      },
      {
        "room_id": 32191149,
        "name": "Phòng có giường King - Không hút thuốc (One King Bed Non Smoking)",
        "features": [],
        "image_count": 4,
        "bed_summary": {
          "symbol": "ficon-bed",
          "title": "1 giường lớn",
          "isAvailable": true,
          "id": 15,
          "value": 0.0,
          "associatedFilters": [
            "twin-bed",
            "double-bed"
          ],
          "targetType": 0,
          "hasDescription": false
        }
      }
    ]
  },
  "description_short": "Nằm ở vị trí trung tâm tại Trung Tâm Mercury của Hampton (VA), chỗ nghỉ này đặt quý khách ở gần các điểm thu hút và tùy chọn ăn uống thú vị.",
  "activities": [
    {
      "activity_id": 1045775,
      "title": "Ưu Đãi Đông - Tour Ngắm Sao Guam (HDV Hàn, Hỗ Trợ Sao)",
      "description": "- Tham gia tour ngắm sao Guam, chiêm ngưỡng các chòm sao như bước ra từ thần thoại Hy Lạp, ánh sao tuyệt đẹp và cảnh đêm quyến rũ của Guam.\n- Thư giãn thoải mái với đồ ăn nhẹ, thức uống và thảm nằm để",
      "review_score": 4.3,
      "review_count": 82,
      "price": {
        "currency": "VND",
        "display": {
          "perBook": {
            "displayType": "BOOK",
            "quantity": 1,
            "total": {
              "allInclusive": {
                "chargeTotal": 961135.0,
                "crossedOut": 1019231.0
              }
            }
          }
        }
      }
    },
    {
      "activity_id": 1043927,
      "title": "Fish Eye Marine Park - Chương Trình Bữa Tối Văn Hóa - Guam",
      "description": "Tận hưởng bữa tối lãng mạn tại Công viên Hải dương Fish Eye ở Guam, nơi bạn có thể thưởng thức chương trình biểu diễn văn hóa sôi động.\n- Hòa mình vào không khí tiệc tùng với những giai điệu du dương,",
      "review_score": 4.7,
      "review_count": 73,
      "price": {
        "currency": "VND",
        "display": {
          "perBook": {
            "displayType": "BOOK",
            "quantity": 1,
            "total": {
              "allInclusive": {
                "chargeTotal": 1717439.0,
                "crossedOut": 1949420.0
              }
            }
          }
        }
      }
    },
    {
      "activity_id": 1051250,
      "title": "Vé Vòng Xoay Mặt Trời High Roller Tại Las Vegas (Kèm Đồ Uống)",
      "description": "Lên đỉnh bánh xe quan sát cao nhất thế giới và ngắm nhìn khung cảnh không bị cản trở của Dải Las Vegas rực rỡ. Làm ướt còi của bạn bằng rượu uống thỏa thích khi đi vòng đu quay!\nLên",
      "review_score": 4.6,
      "review_count": 18,
      "price": {
        "currency": "VND",
        "display": {
          "perBook": {
            "displayType": "BOOK",
            "quantity": 1,
            "total": {
              "allInclusive": {
                "chargeTotal": 798314.0,
                "crossedOut": 842993.0
              }
            }
          }
        }
      }
    },
    {
      "activity_id": 1044391,
      "title": "Tour Có Hướng Dẫn Hẻm Núi Antelope Thượng - Arizona",
      "description": "- Khám phá sa mạc hùng vĩ của Mỹ và chiêm ngưỡng những kỳ quan thiên nhiên độc đáo của Arizona\n- Hẻm Núi Antelope Thượng là một trong những điểm chụp ảnh nổi tiếng thế giới, lý tưởng để ghi lại những",
      "review_score": 4.6,
      "review_count": 41,
      "price": {
        "currency": "VND",
        "display": {
          "perBook": {
            "displayType": "BOOK",
            "quantity": 1,
            "total": {
              "allInclusive": {
                "chargeTotal": 4613014.0,
                "crossedOut": 5136986.0
              }
            }
          }
        }
      }
    },
    {
      "activity_id": 1098564,
      "title": "Tour du ngoạn ngắm cá heo xanh ở Guam (bao gồm sashimi cá ngừ, bia và đồ uống)",
      "description": "Đặt \"Tour du thuyền ngắm cá heo đảo Guam\" cùng KKday ngay hôm nay để chứng kiến những 'chú bé đô con' màu xanh lượn lờ và nô đùa cùng làn nước trong vắt. Thưởng thức món sashimi cá ngừ tươi ngon và",
      "review_score": 4.5,
      "review_count": 21,
      "price": {
        "currency": "VND",
        "display": {
          "perBook": {
            "displayType": "BOOK",
            "quantity": 1,
            "total": {
              "allInclusive": {
                "chargeTotal": 1217175.0,
                "crossedOut": 1234457.0
              }
            }
          }
        }
      }
    },
    {
      "activity_id": 1003600,
      "title": "American Dream DreamWorks Indoor Water Park Ticket",
      "description": "On top of being the largest of its kind in North America, DreamWorks Water Park was awarded the title of #1 indoor water park in the US by USA Today. It's the first ever DreamWorks Water Park open yea",
      "review_score": 3.7,
      "review_count": 146,
      "price": {
        "currency": "VND",
        "display": {
          "perBook": {
            "displayType": "BOOK",
            "quantity": 1,
            "total": {
              "allInclusive": {
                "chargeTotal": 226554.0,
                "crossedOut": 236240.0
              }
            }
          }
        }
      }
    },
    {
      "activity_id": 979944,
      "title": "World of Coca-Cola General Admission Ticket",
      "description": "Step inside a world of fun flavors, iconic stories, and moments of real magic. From tasting your way around the globe to meeting the Coca-Cola Polar Bear, there's a surprise waiting around every corne",
      "review_score": 4.0,
      "review_count": 1104,
      "price": {
        "currency": "VND",
        "display": {
          "perBook": {
            "displayType": "BOOK",
            "quantity": 1,
            "total": {
              "allInclusive": {
                "chargeTotal": 663155.0,
                "crossedOut": 663155.0
              }
            }
          }
        }
      }
    },
    {
      "activity_id": 1042728,
      "title": "Vé vào cửa Thủy cung Shark Reef tại Las Vegas",
      "description": "Khám phá thế giới đại dương kỳ thú tại Shark Reef Aquarium ở Las Vegas, nơi du khách có thể chiêm ngưỡng những loài cá mập và sinh vật biển ấn tượng. Tận hưởng hành trình đi xuyên qua các đường hầm kí",
      "review_score": 0.0,
      "review_count": 0,
      "price": {
        "currency": "VND",
        "display": {
          "perBook": {
            "displayType": "BOOK",
            "quantity": 1,
            "total": {
              "allInclusive": {
                "chargeTotal": 724941.0,
                "crossedOut": 783720.0
              }
            }
          }
        }
      }
    },
    {
      "activity_id": 1588740,
      "title": "Tour Lái Xe Tự Túc Âm Thanh - Bờ Nam Grand Canyon",
      "description": null,
      "review_score": 0.0,
      "review_count": 0,
      "price": {
        "currency": "VND",
        "display": {
          "perBook": {
            "displayType": "BOOK",
            "quantity": 1,
            "total": {
              "allInclusive": {
                "chargeTotal": 450464.0,
                "crossedOut": 491773.0
              }
            }
          }
        }
      }
    },
    {
      "activity_id": 1598002,
      "title": "Natural Bridge Caverns: Hidden Wonders Tour Day Tours",
      "description": null,
      "review_score": 0.0,
      "review_count": 0,
      "price": {
        "currency": "VND",
        "display": {
          "perBook": {
            "displayType": "BOOK",
            "quantity": 1,
            "total": {
              "allInclusive": {
                "chargeTotal": 775528.0,
                "crossedOut": 846646.0
              }
            }
          }
        }
      }
    }
  ],
  "faq": [
    {
      "question": "Days Inn by Hampton Near Coliseum Convention Center có bể bơi không?",
      "answer": "Trong thời gian lưu trú tại Days Inn by Hampton Near Coliseum Convention Center, quý khách có thể bắt đầu ngày mới bằng cách nhảy ùm xuống làn nước mát của bể bơi tại cơ sở lưu trú hoặc chỉ đơn giản là nằm thư giãn bên bể bơi sau một ngày dài khám phá.",
      "category": "property_faq_hotel_facilities_things-to-do"
    },
    {
      "question": "Days Inn by Hampton Near Coliseum Convention Center có dịch vụ giặt là không?",
      "answer": "Có! Days Inn by Hampton Near Coliseum Convention Center cung cấp dịch vụ giặt là để quý khách sử dụng bất cứ khi nào cần quần áo mới sạch thơm trong suốt kỳ nghỉ của mình. Vui lòng liên hệ với cơ sở lưu trú để biết thêm thông tin.",
      "category": "property_faq_hotel_facilities_cleaning"
    },
    {
      "question": "Có các điểm tham quan nào gần Days Inn by Hampton Near Coliseum Convention Center và trong khoảng cách đi bộ?",
      "answer": "Trong thời gian lưu trú tại Days Inn by Hampton Near Coliseum Convention Center, hãy bắt đầu kỳ nghỉ bằng cách khám phá các địa điểm gần nhất trong khoảng cách đi bộ đến cơ sở lưu trú như Bluebird Gap Farm.",
      "category": "property_faq_location_landmark"
    },
    {
      "question": "Chính sách về giường ngủ cho trẻ em tại Days Inn by Hampton Near Coliseum Convention Center",
      "answer": "Chính sách Giường ngủ cho trẻ em tại Days Inn by Hampton Near Coliseum Convention Center tính trẻ 2 tuổi trở lên là người lớn và phải sử dụng giường phụ (có phụ phí). Quý khách có thể tìm thêm thông tin về Chính sách cụ thể cho Trẻ em và Độ tuổi của cơ sở lưu trú này tại phần Chính sách Cơ sở lưu trú nằm tại trang thông tin cơ sở lưu trú để biết thêm chi tiết.",
      "category": "property_faq_property_policies_family"
    },
    {
      "question": "Tại Days Inn by Hampton Near Coliseum Convention Center, khách thường lưu trú trong bao lâu?",
      "answer": "Khách trước đây đã được xác thực lưu trú tạiDays Inn by Hampton Near Coliseum Convention Center có thời gian lưu trú trung bình mỗi đêm là 1 đêm tại cơ sở lưu trú này.",
      "category": "property_faq_property_info_stay"
    },
    {
      "question": "Mùa cao điểm trong năm tại Days Inn by Hampton Near Coliseum Convention Center",
      "answer": "July là mùa cao điểm trong năm tại Days Inn by Hampton Near Coliseum Convention Center. Đây là khoảng thời gian du khách đã xác thực lưu trú nhiều nhất tại đây.",
      "category": "property_faq_property_info_stay"
    },
    {
      "question": "Điều gì ở Days Inn by Hampton Near Coliseum Convention Center được khách yêu thích nhất?",
      "answer": "Khách đã xác thực lưu trú tại Days Inn by Hampton Near Coliseum Convention Center đã đánh giá 8.413 cho cơ sở lưu trú này vì location hiếm có như là điểm nhấn chính cho kỳ lưu trú của họ.",
      "category": "property_faq_review_topic"
    },
    {
      "question": "Điểm trung bình từ khách đi một mình dành cho Days Inn by Hampton Near Coliseum Convention Center",
      "answer": "7.8 là điểm số trung bình của khách đi một mình trước đây đã nghỉ tại Days Inn by Hampton Near Coliseum Convention Center đánh giá cơ sở lưu trú này. Quý khách có thể xem các đánh giá chi tiết hơn của khách hàng và nhận xét bằng cách lọc theo đối tượng khách đã được xác thực ở phần đánh giá.",
      "category": "property_faq_review_traveler_type"
    },
    {
      "question": "Điểm trung bình từ khách cặp đôi dành cho Days Inn by Hampton Near Coliseum Convention Center",
      "answer": "7.8 là điểm số trung bình của khách cặp đôi trước đây đã nghỉ tại Days Inn by Hampton Near Coliseum Convention Center đánh giá cơ sở lưu trú này. Quý khách có thể xem các đánh giá chi tiết hơn của khách hàng và nhận xét bằng cách lọc theo đối tượng khách đã được xác thực ở phần đánh giá.",
      "category": "property_faq_review_traveler_type"
    },
    {
      "question": "Du khách nội địa nghĩ gì về Days Inn by Hampton Near Coliseum Convention Center?",
      "answer": "Du khách nội địa đã từng ở tại Days Inn by Hampton Near Coliseum Convention Center đánh giá trung bình 6.5 cho cơ sở lưu trú này. Quý khách có thể xem các đánh giá chi tiết hơn của khách hàng và nhận xét về cơ sở lưu trú này ở phần đánh giá.",
      "category": "property_faq_review_traveler_type"
    },
    {
      "question": "Giờ nhận phòng và trả phòng ở Days Inn by Hampton Near Coliseum Convention Center",
      "answer": "Nhận phòng từ 03:00 PM và trả phòng cho đến 11:00 AM. Quý khách có thể yêu cầu nhận phòng sớm hoặc trả phòng muộn trong lúc đặt phòng, phụ thuộc vào tình trạng phòng trống. Khách nhận phòng hoặc trả phòng trước hoặc sau khoảng thời gian chỉ định có thể phải thanh toán một khoản phụ phí.",
      "category": "property_faq_property_info_property"
    },
    {
      "question": "Sân bay gần Days Inn by Hampton Near Coliseum Convention Center nhất",
      "answer": "Sân bay gần Days Inn by Hampton Near Coliseum Convention Center nhất là Sân bay Quốc tế Newport News / Williamsburg, cách 14.0 km.",
      "category": "property_faq_location_airport"
    }
  ],
  "suitable_for": [
    "Khách đi công tác",
    "Cặp đôi",
    "Khách du lịch một mình",
    "Gia đình có trẻ nhỏ",
    "Gia đình có thanh thiếu niên",
    "Nhóm du khách"
  ],
  "view_types": [],
  "tags": [
    "Bàn tiếp tân [24 giờ]",
    "Cặp đôi",
    "Gia đình có thanh thiếu niên",
    "Gia đình có trẻ nhỏ",
    "Khách du lịch một mình",
    "Khách đi công tác",
    "Nhóm du khách",
    "Nhận/trả phòng [nhanh]",
    "Rút tiền mặt",
    "Thang máy",
    "Wi-Fi miễn phí trong tất cả các phòng!",
    "Điều hòa"
  ],
  "embedding_text": "Days Inn by Hampton Near Coliseum Convention Center - khách sạn 2.0 sao tại Hampton (VA).\nĐịa chỉ: 1918 Coliseum Drive, Trung Tâm Mercury, Hampton (VA), Hoa Kỳ.\nNằm ở vị trí trung tâm tại Trung Tâm Mercury của Hampton (VA), chỗ nghỉ này đặt quý khách ở gần các điểm thu hút và tùy chọn ăn uống thú vị.\nTiện ích: Bàn tiếp tân [24 giờ], Bãi đỗ xe [miễn phí], Bãi đỗ xe [tại chỗ], Bình chữa cháy, Bể bơi, Bể bơi [trong nhà], CCTV bên ngoài chỗ nghỉ, CCTV trong khu vực chung, Cơ sở vật chất cho họp mặt/tiệc lớn, Dịch vụ báo thức, Dịch vụ giặt là, Dịch vụ ủi đồ, Giá treo quần áo, Giãn cách vật lý ít nhất 1 mét, Hành lang ngoài, Internet, Không được bỏ mặc thú cưng, Khử trùng hằng ngày trong tất cả các phòng, Lò vi sóng, Màn bảo vệ ở khu vực chung, Máy bán hàng tự động, Máy sấy tóc, Nhân viên đeo khẩu trang, Nhận/trả phòng [nhanh], Nước đóng chai, Phòng không hút thuốc, Phù hợp cho xe lăn, Quán cà phê, Rút tiền mặt, Sàn gỗ/gỗ miếng.\nĐiểm đánh giá 7.5/10 dựa trên 515 đánh giá.\nKhách hay nhắc đến: Độ sạch sẽ, Dịch vụ, Địa điểm, Bữa sáng, Độ thoải mái của phòng, Đáng tiền, Bể bơi, Vòi sen.\nCác loại phòng: Two Double Beds Non-Smoking; 1 King Bed Smoking; Phòng có Giường Lớn và Phòng Tắm Có Lối Đi Thoai Thoải - Phù Hợp cho Người Khó Đi Lại, Không Hút Thuốc (1 King Bed, Mobility Accessible Room, Roll-In Shower, Non-Smoking); Two Double Beds Smoking; Phòng có giường King - Phù hợp cho người khuyết tật, không hút thuốc (1 King Bed Accessible Non-Smoking); Phòng có giường King - Không hút thuốc (One King Bed Non Smoking).\nGần: Hampton Roads Convention Center, Bluebird Gap Farm, Green Gates Gifts, Hampton Coliseum, Air Power Park, Hampton Air Power Park & Museum.",
  "_sources_captured": [
    "activities",
    "details",
    "faq",
    "reviews",
    "rooms",
    "secondary"
  ]
}