{
  "crawled_at": "2026-06-06T14:32:35",
  "source_url": "https://www.agoda.com/trang-vu-homestay-cu-lao-cham_2/hotel/all/tan-hiep-vn.html?hotel=926872&currency=VND&checkIn=2026-06-16&checkOut=2026-06-17&rooms=1&adults=2&children=0",
  "hotel_id": 926872,
  "name": "Trang Vu Homestay Cu Lao Cham",
  "property_type": "NonHotel",
  "accommodation_type": "Nhà dân",
  "star_rating": 4.0,
  "is_luxury": false,
  "gold_circle_award_year": null,
  "review_score": 9.2,
  "review_count": 283,
  "address": "BÃI ÔNG, CÙ LAO CHÀM, Tam Hiệp, Tân Hiệp, Việt Nam",
  "area": "Tam Hiệp",
  "city": "Tân Hiệp",
  "country": "Việt Nam",
  "postal_code": "",
  "latitude": 15.960450172424316,
  "longitude": 108.50269317626953,
  "description": "Với Bãi Ông nằm cách đó 2 phút đi bộ, Trang Vu Homestay Cu Lao Cham cung cấp chỗ nghỉ, nhà hàng, khu vườn, phòng chờ chung và sân hiên. WiFi và chỗ đậu xe riêng đều có sẵn tại homestay miễn phí.\n\nMột số căn có TV truyền hình cáp, bếp đầy đủ tiện nghi với tủ lạnh, cùng phòng tắm riêng được trang bị vòi sen và đồ vệ sinh cá nhân miễn phí.\n\nTrang Vu Homestay Cu Lao Cham cách Cù Lao Chàm 3.2 km.",
  "check_in_from": "11:30",
  "check_out_until": "11:00",
  "year_built": null,
  "number_of_floors": null,
  "number_of_rooms": null,
  "useful_info": {
    "Nhận phòng từ": "11:30",
    "Trả phòng đến": "11:00",
    "Trả phòng từ": "10:00",
    "Nhận phòng đến": "14:00"
  },
  "highlights": [
    "Wi-Fi miễn phí trong tất cả các phòng!",
    "Nhân viên chăm sóc khách hàng",
    "Điều hòa",
    "Nhận/trả phòng [nhanh]",
    "Vườn"
  ],
  "location_tags": [
    "Chất lượng và tiện nghi phòng tuyệt vời",
    "Dịch vụ chăm sóc khách chuyên nghiệp",
    "Rất sạch sẽ",
    "Thích hợp cho các hoạt động",
    "Đáng tiền nhất"
  ],
  "amenities": [
    "Bãi đỗ xe [miễn phí]",
    "Bơi với ống thở",
    "Bơi xuồng",
    "Bếp chung",
    "Bữa ăn cho trẻ",
    "Câu cá",
    "Có cung cấp hóa đơn",
    "Dịch vụ Internet",
    "Dịch vụ giặt là",
    "Dịch vụ phòng",
    "Dịch vụ thanh toán không sử dụng tiền mặt",
    "Dịch vụ đưa đón",
    "Giữ hành lý",
    "Internet",
    "Không có văn phòng phẩm dùng chung",
    "Lặn",
    "Máy điều hòa ở khu vực chung",
    "Nhà hàng",
    "Nhân viên chăm sóc khách hàng",
    "Nhân viên được đào tạo về giao thức an toàn",
    "Nhận/trả phòng [nhanh]",
    "Nhận/trả phòng [riêng]",
    "Phòng chờ chung/khu vực TV",
    "Phòng gia đình",
    "Phòng không hút thuốc",
    "Sân hiên",
    "Thích hợp cho gia đình/trẻ em",
    "Tiếng Anh",
    "Vườn",
    "Wi-Fi miễn phí trong tất cả các phòng!",
    "Wi-Fi ở nơi công cộng",
    "bộ dụng cụ sơ cứu",
    "khẩu trang miễn phí",
    "tiếng Việt",
    "Điều hòa",
    "Được phép đưa thú nuôi vào"
  ],
  "amenities_count": 36,
  "amenity_groups": {
    "Ngôn ngữ được sử dụng": [
      "Tiếng Anh",
      "tiếng Việt"
    ],
    "Truy cập Internet": [
      "Dịch vụ Internet",
      "Internet",
      "Wi-Fi miễn phí trong tất cả các phòng!",
      "Wi-Fi ở nơi công cộng"
    ],
    "Thư giãn & Vui chơi giải trí": [
      "Bơi với ống thở",
      "Bơi xuồng",
      "Câu cá",
      "Lặn",
      "Vườn"
    ],
    "Độ sạch sẽ và an toàn": [
      "Dịch vụ thanh toán không sử dụng tiền mặt",
      "Không có văn phòng phẩm dùng chung",
      "Nhân viên được đào tạo về giao thức an toàn",
      "bộ dụng cụ sơ cứu",
      "khẩu trang miễn phí"
    ],
    "Ăn uống": [
      "Bếp chung",
      "Dịch vụ phòng",
      "Nhà hàng"
    ],
    "Dịch vụ và tiện nghi": [
      "Có cung cấp hóa đơn",
      "Dịch vụ giặt là",
      "Giữ hành lý",
      "Máy điều hòa ở khu vực chung",
      "Nhân viên chăm sóc khách hàng",
      "Phòng chờ chung/khu vực TV",
      "Sân hiên"
    ],
    "Dành cho trẻ em": [
      "Bữa ăn cho trẻ",
      "Phòng gia đình",
      "Thích hợp cho gia đình/trẻ em"
    ],
    "Dễ dàng tiếp cận": [
      "Nhận/trả phòng [nhanh]",
      "Nhận/trả phòng [riêng]",
      "Phòng không hút thuốc",
      "Được phép đưa thú nuôi vào"
    ],
    "Đi lại": [
      "Bãi đỗ xe [miễn phí]",
      "Dịch vụ đưa đón"
    ]
  },
  "amenities_general": [
    "Bãi đỗ xe [miễn phí]",
    "Bữa ăn cho trẻ",
    "Có cung cấp hóa đơn",
    "Dịch vụ Internet",
    "Dịch vụ giặt là",
    "Dịch vụ thanh toán không sử dụng tiền mặt",
    "Dịch vụ đưa đón",
    "Giữ hành lý",
    "Internet",
    "Không có văn phòng phẩm dùng chung",
    "Máy điều hòa ở khu vực chung",
    "Nhân viên chăm sóc khách hàng",
    "Nhân viên được đào tạo về giao thức an toàn",
    "Nhận/trả phòng [nhanh]",
    "Nhận/trả phòng [riêng]",
    "Phòng chờ chung/khu vực TV",
    "Phòng gia đình",
    "Phòng không hút thuốc",
    "Sân hiên",
    "Thích hợp cho gia đình/trẻ em",
    "Tiếng Anh",
    "Wi-Fi miễn phí trong tất cả các phòng!",
    "Wi-Fi ở nơi công cộng",
    "bộ dụng cụ sơ cứu",
    "khẩu trang miễn phí",
    "tiếng Việt",
    "Được phép đưa thú nuôi vào"
  ],
  "amenities_leisure": [
    "Bơi với ống thở",
    "Bơi xuồng",
    "Câu cá",
    "Lặn",
    "Vườn"
  ],
  "amenities_dining": [
    "Bếp chung",
    "Dịch vụ phòng",
    "Nhà hàng"
  ],
  "nearby_places": [
    {
      "name": "Cù Lao Chàm",
      "type": "Đảo",
      "distance_km": 1.01
    },
    {
      "name": "Cù Lao Chàm",
      "type": "Đảo",
      "distance_km": 1.61
    },
    {
      "name": "Hòn Tai",
      "type": "Đảo",
      "distance_km": 6.93
    },
    {
      "name": "Sân bay Quốc tế Đà Nẵng",
      "type": "Sân Bay",
      "distance_km": 33.99
    },
    {
      "name": "Sân bay Chu Lai",
      "type": "Sân Bay",
      "distance_km": 64.45
    },
    {
      "name": "Sân bay Quốc tế Phú Bài",
      "type": "Sân Bay",
      "distance_km": 98.56
    }
  ],
  "image_count": 79,
  "image_urls": [
    "https://q-xx.bstatic.com/xdata/images/hotel/max1024x768/103340832.jpg?k=7805f33c257ef971bc958aa8d8e7f9af8428159e410296b56ba946d0754d6dbe&o=",
    "https://q-xx.bstatic.com/xdata/images/hotel/max1024x768/188895158.jpg?k=b2689a832f704ee399527fbf82603bb32cbf863bfcc9afcd6c9e8bdfb1158c8c&o=",
    "https://q-xx.bstatic.com/xdata/images/hotel/max1024x768/103391439.jpg?k=6124ca9e6bc7e9ff5953e91c3deab266a68e54f1adca8ca0c6bd7275a2b4aac6&o=",
    "https://q-xx.bstatic.com/xdata/images/hotel/max1024x768/103391210.jpg?k=6cc5f1cbb70494cb27b69152a8084b9aa7eff8fb4839e60d3413ac3ef6c022b2&o=",
    "https://q-xx.bstatic.com/xdata/images/hotel/max1024x768/103391208.jpg?k=336d0242c9955560b97ed3c5e2b83713ec5daa9b1324a2bf0ab97ce1c42d1903&o=",
    "https://q-xx.bstatic.com/xdata/images/hotel/max1024x768/103391435.jpg?k=2db1a3519305df9f447bc2e48591ef4f3dcf54fb501090cc6f33cb59282b18dd&o=",
    "https://q-xx.bstatic.com/xdata/images/hotel/max1024x768/103391730.jpg?k=0b2695213f2eaa7c52f182148857678e55a705eb07c54bfe906c35c00058e7b3&o=",
    "https://q-xx.bstatic.com/xdata/images/hotel/max1024x768/103391721.jpg?k=3d129b523737d9ab9340b1b217ddb9bdcb6b4b64d5e78dfb2ab690b6dabb2f35&o=",
    "https://q-xx.bstatic.com/xdata/images/hotel/max1024x768/103391211.jpg?k=2847f2ee7f1fef31ad2c006641afa9b73548cd17107b1ede41ee6f72dba83c9b&o=",
    "https://q-xx.bstatic.com/xdata/images/hotel/max1024x768/188904233.jpg?k=f56220715d37476b219ea39c46ecc926a59ca45352b7de1e3d4a37fb7cd54399&o=",
    "https://q-xx.bstatic.com/xdata/images/hotel/max1024x768/103393968.jpg?k=49909379520f450062285d9bb2419a7d611ff8be936f9d6ffefea4c8628f439a&o=",
    "https://q-xx.bstatic.com/xdata/images/hotel/max1024x768/134878669.jpg?k=2de39c95f157bd6405c8eb18865a29c4c5f21f3e34cddb0868c9db876cc3008f&o=",
    "https://q-xx.bstatic.com/xdata/images/hotel/max1024x768/188895163.jpg?k=d2d39169083290842cdf6fee8b14f755762b90cf882bb35115b674875b94ebb7&o=",
    "https://q-xx.bstatic.com/xdata/images/hotel/max1024x768/103391097.jpg?k=b5378e5be3a77c1c84549878461db074b038d49f72c19ee003bf5b73cee168e8&o=",
    "https://q-xx.bstatic.com/xdata/images/hotel/max1024x768/103391095.jpg?k=60edd6035438ecaa93fefd074c6cf14dff18268aabb8114b014e96072f268440&o=",
    "https://q-xx.bstatic.com/xdata/images/hotel/max1024x768/192471453.jpg?k=7b25637137b56ebbc0c80ad267be8c330c07f38d4f2671ea899fa28268f24b10&o=",
    "https://q-xx.bstatic.com/xdata/images/hotel/max1024x768/194756376.jpg?k=2dcffa4ce6d25b6a18412792b5f78fd7b58b4c88eaf2e087f9970863a5385300&o=",
    "https://q-xx.bstatic.com/xdata/images/hotel/max1024x768/103393966.jpg?k=05157cdf2f5b64f4db767e5d82f753b02338677ddd306e3ff67d1a3e06ca9618&o=",
    "https://q-xx.bstatic.com/xdata/images/hotel/max1024x768/188895157.jpg?k=87017a07de6e53f43a3c17855096dfd4b1b8210867a91a6d2dd38b19e697a678&o=",
    "https://q-xx.bstatic.com/xdata/images/hotel/max1024x768/103391093.jpg?k=9e6782e0ae9545c802e57bfcbd9eb2f66f5cdfaac801772d8d270eda6e0370d9&o=",
    "https://q-xx.bstatic.com/xdata/images/hotel/max1024x768/105146607.jpg?k=76d1e69f058cdce21c7647fd1e93394741dbf9db1592b47e17c06860cd209616&o=",
    "https://q-xx.bstatic.com/xdata/images/hotel/max1024x768/103393969.jpg?k=d7d70aba2baa265b593056ceda92dbd5767b97e5660d7a30f2a300a406c6a845&o=",
    "https://q-xx.bstatic.com/xdata/images/hotel/max1024x768/103393957.jpg?k=0a3d379d999efc2aebdfed266d7ace7665bc6dcd44fe7ad2127485a7f2cc0a80&o=",
    "https://q-xx.bstatic.com/xdata/images/hotel/max1024x768/103392881.jpg?k=eccd31a66e92cd05614e373242576ab7cb058de26215238d38904f1e7754a2c5&o=",
    "https://q-xx.bstatic.com/xdata/images/hotel/max1024x768/103344413.jpg?k=d18669b8c115f98e7188a976bca067dd3b65b00abc4e1d596f063b995d544867&o=",
    "https://q-xx.bstatic.com/xdata/images/hotel/max1024x768/103391090.jpg?k=ccc11071187b54ef2acb6a77842ec2873477b84f55896ff394a5d9936e761c00&o=",
    "https://q-xx.bstatic.com/xdata/images/hotel/max1024x768/134878796.jpg?k=31046b9f59807b92e9417cc83bfc62d86b4efa4e13e00905d525b59e156d6144&o=",
    "https://q-xx.bstatic.com/xdata/images/hotel/max1024x768/103344410.jpg?k=392903ed8f97f6ee7ab76e9fa91e1bac0e0f4c6d4d178669c2b8ec8f3d5edf3d&o=",
    "https://q-xx.bstatic.com/xdata/images/hotel/max1024x768/177773804.jpg?k=899c1bcee2f9f340cda565eac29bc6eb5db599544e4282f26309049a1bf9efb4&o=",
    "https://q-xx.bstatic.com/xdata/images/hotel/max1024x768/103344437.jpg?k=8191f2d129c822dfbc55648871824e72ee9c953c4f4615c77a4b54d9c1cb98b9&o=",
    "https://q-xx.bstatic.com/xdata/images/hotel/max1024x768/103393959.jpg?k=f4c2d2af70116a8018a15a2861fc6d8dc7e5012431c47b2edd99b4bba5240460&o=",
    "https://q-xx.bstatic.com/xdata/images/hotel/max1024x768/103391099.jpg?k=2d6870db26f253b9fb372d51715fbc956b02a56b629eba64155acf36e0c02955&o=",
    "https://q-xx.bstatic.com/xdata/images/hotel/max1024x768/103393958.jpg?k=0c8dbe68b1beac3bc25d630fc70db2ca2baad09ec097dcc5d741069ad17dc18e&o=",
    "https://q-xx.bstatic.com/xdata/images/hotel/max1024x768/103393967.jpg?k=a6f7672fc77368f16937e2c4416e6f52926362e0366db837f8e237c46da77c1b&o=",
    "https://q-xx.bstatic.com/xdata/images/hotel/max1024x768/103393974.jpg?k=8a87d33aecedfbeee2714414a33a0ec5e8c47b11ab64c43a651e33c32789f522&o=",
    "https://q-xx.bstatic.com/xdata/images/hotel/max1024x768/103393963.jpg?k=b9a9475c49d537d48ded5d290d006547eff56ba4177d008aafd8b28556da84a4&o=",
    "https://q-xx.bstatic.com/xdata/images/hotel/max1024x768/103344420.jpg?k=286d9d4181f7ca3da4fa15ac888ce2eae323d9536a8737e25262f3d668cc9e30&o=",
    "https://q-xx.bstatic.com/xdata/images/hotel/max1024x768/103393961.jpg?k=d6d21117ff3f96206e9fa2018f9730b220c26ce81abd034f0ff8f81a15226ba0&o=",
    "https://q-xx.bstatic.com/xdata/images/hotel/max1024x768/103392883.jpg?k=159b889761e692f5dc45be27e10b70717c0385be2599f0d3e578569c1f93548a&o=",
    "https://q-xx.bstatic.com/xdata/images/hotel/max1024x768/103393976.jpg?k=6ba06ceb4fe44692e181f228178b07097706367b47da0de8305b40f78bb54aea&o=",
    "https://q-xx.bstatic.com/xdata/images/hotel/max1024x768/103392642.jpg?k=a8fa3e488ea8ee957f2001f2591159b00a27db74921362e6fd3f8e6abc768e56&o=",
    "https://q-xx.bstatic.com/xdata/images/hotel/max1024x768/194756182.jpg?k=a6d3390695963fc9886c5177baaeb19540cbe47962c4bc81dc91ca23136b36d2&o=",
    "https://q-xx.bstatic.com/xdata/images/hotel/max1024x768/103393954.jpg?k=6a608ce5a263a1ada4c39644a7c6ebaa045955b4861350190769e6815a0978c9&o=",
    "https://q-xx.bstatic.com/xdata/images/hotel/max1024x768/103393951.jpg?k=cb0e9f9063d1001709d03c60ab584d97522804f968baa3d4e3e490de43680348&o=",
    "https://q-xx.bstatic.com/xdata/images/hotel/max1024x768/103393972.jpg?k=0e359e4b6dbdbbe2774ccd3e6142a9516c8c22d5cb5aaee55a4a332d80dc99ff&o=",
    "https://q-xx.bstatic.com/xdata/images/hotel/max1024x768/103393956.jpg?k=fb7b80c890203ca336eb37c951928e98870c5908ee46b96a50c45aea1401242e&o=",
    "https://q-xx.bstatic.com/xdata/images/hotel/max1024x768/103392638.jpg?k=88454db0d551cb247cd034b205bbdbc8be8709093e1bd96582524e7285459bd7&o=",
    "https://q-xx.bstatic.com/xdata/images/hotel/max1024x768/103392640.jpg?k=6627f9a8fa4633b0eb9667aa5623ad8a3590ae3e9b01f431f44991820cdf7c43&o=",
    "https://q-xx.bstatic.com/xdata/images/hotel/max1024x768/103392875.jpg?k=ca5411b5392f67a9b56a621c9584e94086687807cfa72466edb0409a08777cf7&o=",
    "https://q-xx.bstatic.com/xdata/images/hotel/max1024x768/103392880.jpg?k=4b768aba786bf1c8c4e92b06ec816c396635e2be3e6c479bf3f8e47f875e7302&o=",
    "https://q-xx.bstatic.com/xdata/images/hotel/max1024x768/336342540.jpg?k=a6c911647819d194c0e15756d254aabeb2e99227f3ad000bba83c6a8378d7364&o=",
    "https://q-xx.bstatic.com/xdata/images/hotel/max1024x768/103391443.jpg?k=8bcb90b0c2715e4652c20b9c449a845e47f81162810cc35cb1d3ae9a50b72e2d&o=",
    "https://q-xx.bstatic.com/xdata/images/hotel/max1024x768/116599873.jpg?k=d627a24f26a03f3f73d518eabaabdc218f03db685975cd8e15854740521ffb0f&o=",
    "https://q-xx.bstatic.com/xdata/images/hotel/max1024x768/103391447.jpg?k=a305bb19e0066cc02fcb8b6e36ec637d7cad682c99d9ec922d07a1d2002f2abf&o=",
    "https://q-xx.bstatic.com/xdata/images/hotel/max1024x768/336342249.jpg?k=77864f03a838b5c742e155043b6c667a5c763c7fb14862bd88c720ac3abf6545&o=",
    "https://q-xx.bstatic.com/xdata/images/hotel/max1024x768/336341816.jpg?k=1655271925b62565a0fdf057c0ccab351ad0a2b442f94c8f4cd1ca9f9a044b5f&o=",
    "https://q-xx.bstatic.com/xdata/images/hotel/max1024x768/103391712.jpg?k=9440b664388194579be570bec42357a4b1f129c69a6aca3c928fb47f7c57a49d&o=",
    "https://q-xx.bstatic.com/xdata/images/hotel/max1024x768/103392110.jpg?k=8e65100f950158c5b80b64bf23338b25d3d9c07d6e2cb16049e9dfe8f778a778&o=",
    "https://q-xx.bstatic.com/xdata/images/hotel/max1024x768/134878636.jpg?k=784209cfc12bb3300bf867c200d1f9787fdea1063ba40a63c4d9455a19a4314b&o=",
    "https://q-xx.bstatic.com/xdata/images/hotel/max1024x768/103393950.jpg?k=8db56a758ad3ec2eb4c8f34deffd12809b2070ca96552ae7fbd6df28e9121411&o=",
    "https://q-xx.bstatic.com/xdata/images/hotel/max1024x768/103393948.jpg?k=e2c86ca968c1e0fec93660320955fbae423b3439dd431303f69110000d4fdde8&o=",
    "https://q-xx.bstatic.com/xdata/images/hotel/max1024x768/105147308.jpg?k=f36416538235aebbc7926cb0e3c5bf8b83a57a945c9ac9147406f58aa9779435&o=",
    "https://q-xx.bstatic.com/xdata/images/hotel/max1024x768/336341563.jpg?k=754dd49da636c2656cbe4ea19fd6344c46584373f9c7766436bdce8e76855df6&o=",
    "https://q-xx.bstatic.com/xdata/images/hotel/max1024x768/103392113.jpg?k=74ed17f3850f5b1606cc80e795b24638f8dd7f44c0d9ad7a92b81be726fab603&o=",
    "https://q-xx.bstatic.com/xdata/images/hotel/max1024x768/134878519.jpg?k=d552f94d5a60379aac90eacc25873a960c5384b672bbde85b6a12a9ed61ee37f&o=",
    "https://q-xx.bstatic.com/xdata/images/hotel/max1024x768/103392643.jpg?k=82cd905a6f7cfcb14a2fb4506dc6c47dca8a2b3a82b774934f03bbb14ba88afe&o=",
    "https://q-xx.bstatic.com/xdata/images/hotel/max1024x768/134878483.jpg?k=cbf43aa38a85bc1ef671553e0b6b6849ff4df598f930bbf82aef46b90ca5ee7e&o=",
    "https://q-xx.bstatic.com/xdata/images/hotel/max1024x768/103392877.jpg?k=70810381784fa25e94e5d11d83a970fdc38d397f06c63763f1942732dab8f220&o=",
    "https://q-xx.bstatic.com/xdata/images/hotel/max1024x768/134878384.jpg?k=5449c42253400c163fb1cbe387d1547e4858cdc2c58184eb3b4439ac408dfe7d&o=",
    "https://q-xx.bstatic.com/xdata/images/hotel/max1024x768/103391709.jpg?k=826f7d53f18042e25badbfae3f9fc2ff223dee0d3cadf0e420f4c2dc9fa0d1d5&o=",
    "https://q-xx.bstatic.com/xdata/images/hotel/max1024x768/103392107.jpg?k=8a366ba38640eca222b2d04f1dce320a6e829fbf234eced8502a24369d811c04&o=",
    "https://q-xx.bstatic.com/xdata/images/hotel/max1024x768/103392644.jpg?k=8ada8f8e270b59c3786044808fc7f37c8a2f617082f9c2948d5e934ee8d1938a&o=",
    "https://q-xx.bstatic.com/xdata/images/hotel/max1024x768/134878448.jpg?k=2a4164e7831031f17162c80c14070b6cdfd8350f3a2c4d80a82696516fa545e9&o=",
    "https://q-xx.bstatic.com/xdata/images/hotel/max1024x768/103392111.jpg?k=ddafd8ba2069b8e98e7c54a0f892185eab0c9ad86401997fdab4895faecf8eaa&o=",
    "https://q-xx.bstatic.com/xdata/images/hotel/max1024x768/103391713.jpg?k=bc4be9d34efc4573868e6522e49dfe184a0c3069803146c3a7692829a93a424c&o=",
    "https://q-xx.bstatic.com/xdata/images/hotel/max1024x768/103393949.jpg?k=fb4e3d88ce902ec7b6b9c0063270ea828ecd8badef37d8059464f0e4103993d9&o=",
    "https://q-xx.bstatic.com/xdata/images/hotel/max1024x768/194755947.jpg?k=585458b36bee4903a5289dcdc197884ccb54fa06879535491a5d656c7d4d79d1&o=",
    "https://q-xx.bstatic.com/xdata/images/hotel/max1024x768/103392115.jpg?k=9dadf97761a8b932ab2cbff66295103f4dc5af7c23f2029aaafa5cef62f096d9&o=",
    "https://q-xx.bstatic.com/xdata/images/hotel/max1024x768/336342919.jpg?k=f7b05e4b1d047eb415d46bca2346dce298194a047cb69b81a1acfa6c9aeb346a&o="
  ],
  "images": [
    {
      "url": "https://q-xx.bstatic.com/xdata/images/hotel/max1024x768/103340832.jpg?k=7805f33c257ef971bc958aa8d8e7f9af8428159e410296b56ba946d0754d6dbe&o=",
      "caption": "Cơ sở vật chất",
      "category": "Cơ sở vật chất"
    },
    {
      "url": "https://q-xx.bstatic.com/xdata/images/hotel/max1024x768/188895158.jpg?k=b2689a832f704ee399527fbf82603bb32cbf863bfcc9afcd6c9e8bdfb1158c8c&o=",
      "caption": "",
      "category": "Phòng"
    },
    {
      "url": "https://q-xx.bstatic.com/xdata/images/hotel/max1024x768/103391439.jpg?k=6124ca9e6bc7e9ff5953e91c3deab266a68e54f1adca8ca0c6bd7275a2b4aac6&o=",
      "caption": "Cơ sở vật chất",
      "category": "Cơ sở vật chất"
    },
    {
      "url": "https://q-xx.bstatic.com/xdata/images/hotel/max1024x768/103391210.jpg?k=6cc5f1cbb70494cb27b69152a8084b9aa7eff8fb4839e60d3413ac3ef6c022b2&o=",
      "caption": "Khu vực xung quanh",
      "category": "Cơ sở vật chất"
    },
    {
      "url": "https://q-xx.bstatic.com/xdata/images/hotel/max1024x768/103391208.jpg?k=336d0242c9955560b97ed3c5e2b83713ec5daa9b1324a2bf0ab97ce1c42d1903&o=",
      "caption": "Khu vực xung quanh",
      "category": "Cơ sở vật chất"
    },
    {
      "url": "https://q-xx.bstatic.com/xdata/images/hotel/max1024x768/103391435.jpg?k=2db1a3519305df9f447bc2e48591ef4f3dcf54fb501090cc6f33cb59282b18dd&o=",
      "caption": "Cơ sở vật chất",
      "category": "Cơ sở vật chất"
    },
    {
      "url": "https://q-xx.bstatic.com/xdata/images/hotel/max1024x768/103391730.jpg?k=0b2695213f2eaa7c52f182148857678e55a705eb07c54bfe906c35c00058e7b3&o=",
      "caption": "Cơ sở vật chất",
      "category": "Cơ sở vật chất"
    },
    {
      "url": "https://q-xx.bstatic.com/xdata/images/hotel/max1024x768/103391721.jpg?k=3d129b523737d9ab9340b1b217ddb9bdcb6b4b64d5e78dfb2ab690b6dabb2f35&o=",
      "caption": "Cơ sở vật chất",
      "category": "Cơ sở vật chất"
    },
    {
      "url": "https://q-xx.bstatic.com/xdata/images/hotel/max1024x768/103391211.jpg?k=2847f2ee7f1fef31ad2c006641afa9b73548cd17107b1ede41ee6f72dba83c9b&o=",
      "caption": "Nhà hàng",
      "category": "Ăn uống"
    },
    {
      "url": "https://q-xx.bstatic.com/xdata/images/hotel/max1024x768/188904233.jpg?k=f56220715d37476b219ea39c46ecc926a59ca45352b7de1e3d4a37fb7cd54399&o=",
      "caption": "",
      "category": "Phòng"
    },
    {
      "url": "https://q-xx.bstatic.com/xdata/images/hotel/max1024x768/103393968.jpg?k=49909379520f450062285d9bb2419a7d611ff8be936f9d6ffefea4c8628f439a&o=",
      "caption": "Nơi tham quan gần đây",
      "category": "Nơi tham quan gần đây"
    },
    {
      "url": "https://q-xx.bstatic.com/xdata/images/hotel/max1024x768/134878669.jpg?k=2de39c95f157bd6405c8eb18865a29c4c5f21f3e34cddb0868c9db876cc3008f&o=",
      "caption": "Khu vực xung quanh",
      "category": "Cơ sở vật chất"
    },
    {
      "url": "https://q-xx.bstatic.com/xdata/images/hotel/max1024x768/188895163.jpg?k=d2d39169083290842cdf6fee8b14f755762b90cf882bb35115b674875b94ebb7&o=",
      "caption": "",
      "category": "Khác"
    },
    {
      "url": "https://q-xx.bstatic.com/xdata/images/hotel/max1024x768/103391097.jpg?k=b5378e5be3a77c1c84549878461db074b038d49f72c19ee003bf5b73cee168e8&o=",
      "caption": "Cơ sở vật chất",
      "category": "Cơ sở vật chất"
    },
    {
      "url": "https://q-xx.bstatic.com/xdata/images/hotel/max1024x768/103391095.jpg?k=60edd6035438ecaa93fefd074c6cf14dff18268aabb8114b014e96072f268440&o=",
      "caption": "Cơ sở vật chất",
      "category": "Cơ sở vật chất"
    },
    {
      "url": "https://q-xx.bstatic.com/xdata/images/hotel/max1024x768/192471453.jpg?k=7b25637137b56ebbc0c80ad267be8c330c07f38d4f2671ea899fa28268f24b10&o=",
      "caption": "",
      "category": "Phòng"
    },
    {
      "url": "https://q-xx.bstatic.com/xdata/images/hotel/max1024x768/194756376.jpg?k=2dcffa4ce6d25b6a18412792b5f78fd7b58b4c88eaf2e087f9970863a5385300&o=",
      "caption": "",
      "category": "Cơ sở vật chất"
    },
    {
      "url": "https://q-xx.bstatic.com/xdata/images/hotel/max1024x768/103393966.jpg?k=05157cdf2f5b64f4db767e5d82f753b02338677ddd306e3ff67d1a3e06ca9618&o=",
      "caption": "Nơi tham quan gần đây",
      "category": "Nơi tham quan gần đây"
    },
    {
      "url": "https://q-xx.bstatic.com/xdata/images/hotel/max1024x768/188895157.jpg?k=87017a07de6e53f43a3c17855096dfd4b1b8210867a91a6d2dd38b19e697a678&o=",
      "caption": "",
      "category": "Phòng"
    },
    {
      "url": "https://q-xx.bstatic.com/xdata/images/hotel/max1024x768/103391093.jpg?k=9e6782e0ae9545c802e57bfcbd9eb2f66f5cdfaac801772d8d270eda6e0370d9&o=",
      "caption": "Cơ sở vật chất",
      "category": "Cơ sở vật chất"
    },
    {
      "url": "https://q-xx.bstatic.com/xdata/images/hotel/max1024x768/105146607.jpg?k=76d1e69f058cdce21c7647fd1e93394741dbf9db1592b47e17c06860cd209616&o=",
      "caption": "",
      "category": "Cơ sở vật chất"
    },
    {
      "url": "https://q-xx.bstatic.com/xdata/images/hotel/max1024x768/103393969.jpg?k=d7d70aba2baa265b593056ceda92dbd5767b97e5660d7a30f2a300a406c6a845&o=",
      "caption": "Thể thao và hoạt động",
      "category": "Cơ sở vật chất"
    },
    {
      "url": "https://q-xx.bstatic.com/xdata/images/hotel/max1024x768/103393957.jpg?k=0a3d379d999efc2aebdfed266d7ace7665bc6dcd44fe7ad2127485a7f2cc0a80&o=",
      "caption": "Nơi tham quan gần đây",
      "category": "Nơi tham quan gần đây"
    },
    {
      "url": "https://q-xx.bstatic.com/xdata/images/hotel/max1024x768/103392881.jpg?k=eccd31a66e92cd05614e373242576ab7cb058de26215238d38904f1e7754a2c5&o=",
      "caption": "Khu vực xung quanh",
      "category": "Cơ sở vật chất"
    },
    {
      "url": "https://q-xx.bstatic.com/xdata/images/hotel/max1024x768/103344413.jpg?k=d18669b8c115f98e7188a976bca067dd3b65b00abc4e1d596f063b995d544867&o=",
      "caption": "Cơ sở vật chất",
      "category": "Cơ sở vật chất"
    },
    {
      "url": "https://q-xx.bstatic.com/xdata/images/hotel/max1024x768/103391090.jpg?k=ccc11071187b54ef2acb6a77842ec2873477b84f55896ff394a5d9936e761c00&o=",
      "caption": "Cơ sở vật chất",
      "category": "Cơ sở vật chất"
    },
    {
      "url": "https://q-xx.bstatic.com/xdata/images/hotel/max1024x768/134878796.jpg?k=31046b9f59807b92e9417cc83bfc62d86b4efa4e13e00905d525b59e156d6144&o=",
      "caption": "Nhà hàng",
      "category": "Ăn uống"
    },
    {
      "url": "https://q-xx.bstatic.com/xdata/images/hotel/max1024x768/103344410.jpg?k=392903ed8f97f6ee7ab76e9fa91e1bac0e0f4c6d4d178669c2b8ec8f3d5edf3d&o=",
      "caption": "Cơ sở vật chất",
      "category": "Cơ sở vật chất"
    },
    {
      "url": "https://q-xx.bstatic.com/xdata/images/hotel/max1024x768/177773804.jpg?k=899c1bcee2f9f340cda565eac29bc6eb5db599544e4282f26309049a1bf9efb4&o=",
      "caption": "",
      "category": "Cơ sở vật chất"
    },
    {
      "url": "https://q-xx.bstatic.com/xdata/images/hotel/max1024x768/103344437.jpg?k=8191f2d129c822dfbc55648871824e72ee9c953c4f4615c77a4b54d9c1cb98b9&o=",
      "caption": "Lối vào",
      "category": "Khách sạn"
    },
    {
      "url": "https://q-xx.bstatic.com/xdata/images/hotel/max1024x768/103393959.jpg?k=f4c2d2af70116a8018a15a2861fc6d8dc7e5012431c47b2edd99b4bba5240460&o=",
      "caption": "Nơi tham quan gần đây",
      "category": "Nơi tham quan gần đây"
    },
    {
      "url": "https://q-xx.bstatic.com/xdata/images/hotel/max1024x768/103391099.jpg?k=2d6870db26f253b9fb372d51715fbc956b02a56b629eba64155acf36e0c02955&o=",
      "caption": "Cơ sở vật chất",
      "category": "Cơ sở vật chất"
    },
    {
      "url": "https://q-xx.bstatic.com/xdata/images/hotel/max1024x768/103393958.jpg?k=0c8dbe68b1beac3bc25d630fc70db2ca2baad09ec097dcc5d741069ad17dc18e&o=",
      "caption": "Nơi tham quan gần đây",
      "category": "Nơi tham quan gần đây"
    },
    {
      "url": "https://q-xx.bstatic.com/xdata/images/hotel/max1024x768/103393967.jpg?k=a6f7672fc77368f16937e2c4416e6f52926362e0366db837f8e237c46da77c1b&o=",
      "caption": "Nơi tham quan gần đây",
      "category": "Nơi tham quan gần đây"
    },
    {
      "url": "https://q-xx.bstatic.com/xdata/images/hotel/max1024x768/103393974.jpg?k=8a87d33aecedfbeee2714414a33a0ec5e8c47b11ab64c43a651e33c32789f522&o=",
      "caption": "Tiện nghi giải trí",
      "category": "Cơ sở vật chất"
    },
    {
      "url": "https://q-xx.bstatic.com/xdata/images/hotel/max1024x768/103393963.jpg?k=b9a9475c49d537d48ded5d290d006547eff56ba4177d008aafd8b28556da84a4&o=",
      "caption": "Nơi tham quan gần đây",
      "category": "Nơi tham quan gần đây"
    },
    {
      "url": "https://q-xx.bstatic.com/xdata/images/hotel/max1024x768/103344420.jpg?k=286d9d4181f7ca3da4fa15ac888ce2eae323d9536a8737e25262f3d668cc9e30&o=",
      "caption": "Lối vào",
      "category": "Khách sạn"
    },
    {
      "url": "https://q-xx.bstatic.com/xdata/images/hotel/max1024x768/103393961.jpg?k=d6d21117ff3f96206e9fa2018f9730b220c26ce81abd034f0ff8f81a15226ba0&o=",
      "caption": "Nơi tham quan gần đây",
      "category": "Nơi tham quan gần đây"
    },
    {
      "url": "https://q-xx.bstatic.com/xdata/images/hotel/max1024x768/103392883.jpg?k=159b889761e692f5dc45be27e10b70717c0385be2599f0d3e578569c1f93548a&o=",
      "caption": "Cơ sở vật chất",
      "category": "Cơ sở vật chất"
    },
    {
      "url": "https://q-xx.bstatic.com/xdata/images/hotel/max1024x768/103393976.jpg?k=6ba06ceb4fe44692e181f228178b07097706367b47da0de8305b40f78bb54aea&o=",
      "caption": "Tiện nghi giải trí",
      "category": "Cơ sở vật chất"
    },
    {
      "url": "https://q-xx.bstatic.com/xdata/images/hotel/max1024x768/103392642.jpg?k=a8fa3e488ea8ee957f2001f2591159b00a27db74921362e6fd3f8e6abc768e56&o=",
      "caption": "Cơ sở vật chất",
      "category": "Cơ sở vật chất"
    },
    {
      "url": "https://q-xx.bstatic.com/xdata/images/hotel/max1024x768/194756182.jpg?k=a6d3390695963fc9886c5177baaeb19540cbe47962c4bc81dc91ca23136b36d2&o=",
      "caption": "",
      "category": "Cơ sở vật chất"
    },
    {
      "url": "https://q-xx.bstatic.com/xdata/images/hotel/max1024x768/103393954.jpg?k=6a608ce5a263a1ada4c39644a7c6ebaa045955b4861350190769e6815a0978c9&o=",
      "caption": "Nơi tham quan gần đây",
      "category": "Nơi tham quan gần đây"
    },
    {
      "url": "https://q-xx.bstatic.com/xdata/images/hotel/max1024x768/103393951.jpg?k=cb0e9f9063d1001709d03c60ab584d97522804f968baa3d4e3e490de43680348&o=",
      "caption": "Nơi tham quan gần đây",
      "category": "Nơi tham quan gần đây"
    },
    {
      "url": "https://q-xx.bstatic.com/xdata/images/hotel/max1024x768/103393972.jpg?k=0e359e4b6dbdbbe2774ccd3e6142a9516c8c22d5cb5aaee55a4a332d80dc99ff&o=",
      "caption": "Tiện nghi giải trí",
      "category": "Cơ sở vật chất"
    },
    {
      "url": "https://q-xx.bstatic.com/xdata/images/hotel/max1024x768/103393956.jpg?k=fb7b80c890203ca336eb37c951928e98870c5908ee46b96a50c45aea1401242e&o=",
      "caption": "Nơi tham quan gần đây",
      "category": "Nơi tham quan gần đây"
    },
    {
      "url": "https://q-xx.bstatic.com/xdata/images/hotel/max1024x768/103392638.jpg?k=88454db0d551cb247cd034b205bbdbc8be8709093e1bd96582524e7285459bd7&o=",
      "caption": "Cơ sở vật chất",
      "category": "Cơ sở vật chất"
    },
    {
      "url": "https://q-xx.bstatic.com/xdata/images/hotel/max1024x768/103392640.jpg?k=6627f9a8fa4633b0eb9667aa5623ad8a3590ae3e9b01f431f44991820cdf7c43&o=",
      "caption": "Khu vực xung quanh",
      "category": "Cơ sở vật chất"
    },
    {
      "url": "https://q-xx.bstatic.com/xdata/images/hotel/max1024x768/103392875.jpg?k=ca5411b5392f67a9b56a621c9584e94086687807cfa72466edb0409a08777cf7&o=",
      "caption": "Tiện nghi giải trí",
      "category": "Cơ sở vật chất"
    },
    {
      "url": "https://q-xx.bstatic.com/xdata/images/hotel/max1024x768/103392880.jpg?k=4b768aba786bf1c8c4e92b06ec816c396635e2be3e6c479bf3f8e47f875e7302&o=",
      "caption": "Tiện nghi giải trí",
      "category": "Cơ sở vật chất"
    },
    {
      "url": "https://q-xx.bstatic.com/xdata/images/hotel/max1024x768/336342540.jpg?k=a6c911647819d194c0e15756d254aabeb2e99227f3ad000bba83c6a8378d7364&o=",
      "caption": "Nhà hàng",
      "category": "Ăn uống"
    },
    {
      "url": "https://q-xx.bstatic.com/xdata/images/hotel/max1024x768/103391443.jpg?k=8bcb90b0c2715e4652c20b9c449a845e47f81162810cc35cb1d3ae9a50b72e2d&o=",
      "caption": "Vòi sen",
      "category": "Cơ sở vật chất"
    },
    {
      "url": "https://q-xx.bstatic.com/xdata/images/hotel/max1024x768/116599873.jpg?k=d627a24f26a03f3f73d518eabaabdc218f03db685975cd8e15854740521ffb0f&o=",
      "caption": "",
      "category": "Cơ sở vật chất"
    },
    {
      "url": "https://q-xx.bstatic.com/xdata/images/hotel/max1024x768/103391447.jpg?k=a305bb19e0066cc02fcb8b6e36ec637d7cad682c99d9ec922d07a1d2002f2abf&o=",
      "caption": "Vòi sen",
      "category": "Cơ sở vật chất"
    },
    {
      "url": "https://q-xx.bstatic.com/xdata/images/hotel/max1024x768/336342249.jpg?k=77864f03a838b5c742e155043b6c667a5c763c7fb14862bd88c720ac3abf6545&o=",
      "caption": "Nhà hàng",
      "category": "Ăn uống"
    },
    {
      "url": "https://q-xx.bstatic.com/xdata/images/hotel/max1024x768/336341816.jpg?k=1655271925b62565a0fdf057c0ccab351ad0a2b442f94c8f4cd1ca9f9a044b5f&o=",
      "caption": "",
      "category": "Khác"
    },
    {
      "url": "https://q-xx.bstatic.com/xdata/images/hotel/max1024x768/103391712.jpg?k=9440b664388194579be570bec42357a4b1f129c69a6aca3c928fb47f7c57a49d&o=",
      "caption": "Đồ ăn và thức uống",
      "category": "Ăn uống"
    },
    {
      "url": "https://q-xx.bstatic.com/xdata/images/hotel/max1024x768/103392110.jpg?k=8e65100f950158c5b80b64bf23338b25d3d9c07d6e2cb16049e9dfe8f778a778&o=",
      "caption": "Nhà hàng",
      "category": "Ăn uống"
    },
    {
      "url": "https://q-xx.bstatic.com/xdata/images/hotel/max1024x768/134878636.jpg?k=784209cfc12bb3300bf867c200d1f9787fdea1063ba40a63c4d9455a19a4314b&o=",
      "caption": "",
      "category": "Khách sạn"
    },
    {
      "url": "https://q-xx.bstatic.com/xdata/images/hotel/max1024x768/103393950.jpg?k=8db56a758ad3ec2eb4c8f34deffd12809b2070ca96552ae7fbd6df28e9121411&o=",
      "caption": "Khu vực xung quanh",
      "category": "Cơ sở vật chất"
    },
    {
      "url": "https://q-xx.bstatic.com/xdata/images/hotel/max1024x768/103393948.jpg?k=e2c86ca968c1e0fec93660320955fbae423b3439dd431303f69110000d4fdde8&o=",
      "caption": "Khu vực xung quanh",
      "category": "Cơ sở vật chất"
    },
    {
      "url": "https://q-xx.bstatic.com/xdata/images/hotel/max1024x768/105147308.jpg?k=f36416538235aebbc7926cb0e3c5bf8b83a57a945c9ac9147406f58aa9779435&o=",
      "caption": "",
      "category": "Khách sạn"
    },
    {
      "url": "https://q-xx.bstatic.com/xdata/images/hotel/max1024x768/336341563.jpg?k=754dd49da636c2656cbe4ea19fd6344c46584373f9c7766436bdce8e76855df6&o=",
      "caption": "",
      "category": "Cơ sở vật chất"
    },
    {
      "url": "https://q-xx.bstatic.com/xdata/images/hotel/max1024x768/103392113.jpg?k=74ed17f3850f5b1606cc80e795b24638f8dd7f44c0d9ad7a92b81be726fab603&o=",
      "caption": "Đồ ăn và thức uống",
      "category": "Ăn uống"
    },
    {
      "url": "https://q-xx.bstatic.com/xdata/images/hotel/max1024x768/134878519.jpg?k=d552f94d5a60379aac90eacc25873a960c5384b672bbde85b6a12a9ed61ee37f&o=",
      "caption": "",
      "category": "Khách sạn"
    },
    {
      "url": "https://q-xx.bstatic.com/xdata/images/hotel/max1024x768/103392643.jpg?k=82cd905a6f7cfcb14a2fb4506dc6c47dca8a2b3a82b774934f03bbb14ba88afe&o=",
      "caption": "Đồ ăn và thức uống",
      "category": "Ăn uống"
    },
    {
      "url": "https://q-xx.bstatic.com/xdata/images/hotel/max1024x768/134878483.jpg?k=cbf43aa38a85bc1ef671553e0b6b6849ff4df598f930bbf82aef46b90ca5ee7e&o=",
      "caption": "",
      "category": "Cơ sở vật chất"
    },
    {
      "url": "https://q-xx.bstatic.com/xdata/images/hotel/max1024x768/103392877.jpg?k=70810381784fa25e94e5d11d83a970fdc38d397f06c63763f1942732dab8f220&o=",
      "caption": "Tiện nghi giải trí",
      "category": "Cơ sở vật chất"
    },
    {
      "url": "https://q-xx.bstatic.com/xdata/images/hotel/max1024x768/134878384.jpg?k=5449c42253400c163fb1cbe387d1547e4858cdc2c58184eb3b4439ac408dfe7d&o=",
      "caption": "",
      "category": "Khác"
    },
    {
      "url": "https://q-xx.bstatic.com/xdata/images/hotel/max1024x768/103391709.jpg?k=826f7d53f18042e25badbfae3f9fc2ff223dee0d3cadf0e420f4c2dc9fa0d1d5&o=",
      "caption": "Đồ ăn và thức uống",
      "category": "Ăn uống"
    },
    {
      "url": "https://q-xx.bstatic.com/xdata/images/hotel/max1024x768/103392107.jpg?k=8a366ba38640eca222b2d04f1dce320a6e829fbf234eced8502a24369d811c04&o=",
      "caption": "Nhà hàng",
      "category": "Ăn uống"
    },
    {
      "url": "https://q-xx.bstatic.com/xdata/images/hotel/max1024x768/103392644.jpg?k=8ada8f8e270b59c3786044808fc7f37c8a2f617082f9c2948d5e934ee8d1938a&o=",
      "caption": "Đồ ăn và thức uống",
      "category": "Ăn uống"
    },
    {
      "url": "https://q-xx.bstatic.com/xdata/images/hotel/max1024x768/134878448.jpg?k=2a4164e7831031f17162c80c14070b6cdfd8350f3a2c4d80a82696516fa545e9&o=",
      "caption": "",
      "category": "Khác"
    },
    {
      "url": "https://q-xx.bstatic.com/xdata/images/hotel/max1024x768/103392111.jpg?k=ddafd8ba2069b8e98e7c54a0f892185eab0c9ad86401997fdab4895faecf8eaa&o=",
      "caption": "Đồ ăn và thức uống",
      "category": "Ăn uống"
    },
    {
      "url": "https://q-xx.bstatic.com/xdata/images/hotel/max1024x768/103391713.jpg?k=bc4be9d34efc4573868e6522e49dfe184a0c3069803146c3a7692829a93a424c&o=",
      "caption": "Đồ ăn và thức uống",
      "category": "Ăn uống"
    },
    {
      "url": "https://q-xx.bstatic.com/xdata/images/hotel/max1024x768/103393949.jpg?k=fb4e3d88ce902ec7b6b9c0063270ea828ecd8badef37d8059464f0e4103993d9&o=",
      "caption": "Khu vực xung quanh",
      "category": "Cơ sở vật chất"
    },
    {
      "url": "https://q-xx.bstatic.com/xdata/images/hotel/max1024x768/194755947.jpg?k=585458b36bee4903a5289dcdc197884ccb54fa06879535491a5d656c7d4d79d1&o=",
      "caption": "",
      "category": "Khác"
    },
    {
      "url": "https://q-xx.bstatic.com/xdata/images/hotel/max1024x768/103392115.jpg?k=9dadf97761a8b932ab2cbff66295103f4dc5af7c23f2029aaafa5cef62f096d9&o=",
      "caption": "Đồ ăn và thức uống",
      "category": "Ăn uống"
    },
    {
      "url": "https://q-xx.bstatic.com/xdata/images/hotel/max1024x768/336342919.jpg?k=f7b05e4b1d047eb415d46bca2346dce298194a047cb69b81a1acfa6c9aeb346a&o=",
      "caption": "",
      "category": "Khác"
    }
  ],
  "district": "Tam Hiệp",
  "province": "Tân Hiệp",
  "city_id": 215135,
  "property_page": "/trang-vu-homestay-cu-lao-cham_2/hotel/all/tan-hiep-vn.html",
  "room_grid": {
    "is_sold_out": false,
    "cheapest_price": null,
    "room_count": 5,
    "rooms": [
      {
        "room_type_id": 5692724,
        "name": "Phòng 4 Người (Quadruple Room)",
        "name_en": "(Quadruple Room)",
        "room_size": "30 m²",
        "size_sqm": 30.0,
        "max_occupancy": null,
        "max_occupancy_text": null,
        "bed_type": "2 giường lớn",
        "bed_types": [
          "2 giường lớn"
        ],
        "room_view": "Hướng Núi",
        "is_sold_out": false,
        "facilities": [
          "Hướng Núi",
          "Vòi sen",
          "Phòng tắm chung"
        ],
        "room_amenities": [
          "2 giường lớn",
          "30 m²",
          "Ban công/sân hiên",
          "Bàn trang điểm phù hợp cho người khuyết tật",
          "Bếp đầy đủ",
          "Bố trí và nội thất phòng",
          "Các loại khăn",
          "Cách âm",
          "Dép đi trong nhà",
          "Giá treo quần áo",
          "Giải trí ",
          "Hướng Núi",
          "Khu vực tiếp khách",
          "Khu vực ăn uống riêng",
          "Khả năng tiếp cận cho người khuyết tật",
          "Lối đi riêng",
          "Màn",
          "Nhà vệ sinh phụ",
          "Phòng tắm chung",
          "Phòng tắm phụ",
          "Phòng tắm và vật dụng vệ sinh",
          "Quạt",
          "Quần áo và Giặt ủi",
          "Sàn lát gạch/Sàn đá cẩm thạch",
          "Sản phẩm vệ sinh",
          "TV",
          "Thùng rác",
          "Tiện nghi",
          "Tiện nghi BBQ",
          "Truyền hình cáp/vệ tinh",
          "Tủ lạnh",
          "Vòi sen",
          "Vải trải giường",
          "Vật dụng tắm rửa",
          "phòng tắm riêng",
          "Ăn uống",
          "Điều hòa",
          "Đồ gỗ ngoài trời",
          "Ổ cắm điện gần giường"
        ],
        "price": null,
        "image_count": 1,
        "images": [
          "https://q-xx.bstatic.com/xdata/images/hotel/840x460/103340832.jpg?k=7805f33c257ef971bc958aa8d8e7f9af8428159e410296b56ba946d0754d6dbe&o="
        ],
        "review_score": 8.8
      },
      {
        "room_type_id": 692303030,
        "name": "Phòng Hạng Tiết kiệm Cho 4 Người (Economy Quadruple Room)",
        "name_en": "(Economy Quadruple Room)",
        "room_size": null,
        "size_sqm": null,
        "max_occupancy": null,
        "max_occupancy_text": null,
        "bed_type": "2 giường đôi lớn",
        "bed_types": [
          "2 giường đôi lớn"
        ],
        "room_view": null,
        "is_sold_out": false,
        "facilities": [],
        "room_amenities": [
          "2 giường đôi lớn",
          "Phòng tắm và vật dụng vệ sinh",
          "Tiện nghi",
          "phòng tắm riêng",
          "Điều hòa"
        ],
        "price": null,
        "image_count": 1,
        "images": [
          "https://q-xx.bstatic.com/xdata/images/hotel/840x460/103340832.jpg?k=7805f33c257ef971bc958aa8d8e7f9af8428159e410296b56ba946d0754d6dbe&o="
        ],
        "review_score": 10.0
      },
      {
        "room_type_id": 5692986,
        "name": "Phòng Đôi (Double Room)",
        "name_en": "(Double Room)",
        "room_size": "20 m²",
        "size_sqm": 20.0,
        "max_occupancy": null,
        "max_occupancy_text": null,
        "bed_type": "1 giường lớn",
        "bed_types": [
          "1 giường lớn"
        ],
        "room_view": "Hướng Núi",
        "is_sold_out": false,
        "facilities": [
          "Hướng Núi",
          "Vòi sen",
          "Phòng tắm chung"
        ],
        "room_amenities": [
          "1 giường lớn",
          "20 m²",
          "Ban công/sân hiên",
          "Bàn trang điểm phù hợp cho người khuyết tật",
          "Bếp đầy đủ",
          "Bố trí và nội thất phòng",
          "Các loại khăn",
          "Cách âm",
          "Dép đi trong nhà",
          "Giá treo quần áo",
          "Giải trí ",
          "Hướng Núi",
          "Khu vực tiếp khách",
          "Khu vực ăn uống riêng",
          "Khả năng tiếp cận cho người khuyết tật",
          "Lối đi riêng",
          "Màn",
          "Nhà vệ sinh phụ",
          "Phòng tắm chung",
          "Phòng tắm phụ",
          "Phòng tắm và vật dụng vệ sinh",
          "Quạt",
          "Quần áo và Giặt ủi",
          "Sàn lát gạch/Sàn đá cẩm thạch",
          "Sản phẩm vệ sinh",
          "TV",
          "Thùng rác",
          "Tiện nghi",
          "Tiện nghi BBQ",
          "Truyền hình cáp/vệ tinh",
          "Tủ lạnh",
          "Vòi sen",
          "Vải trải giường",
          "Vật dụng tắm rửa",
          "phòng tắm riêng",
          "Ăn uống",
          "Điều hòa",
          "Đồ gỗ ngoài trời",
          "Ổ cắm điện gần giường"
        ],
        "price": null,
        "image_count": 1,
        "images": [
          "https://q-xx.bstatic.com/xdata/images/hotel/840x460/103340832.jpg?k=7805f33c257ef971bc958aa8d8e7f9af8428159e410296b56ba946d0754d6dbe&o="
        ],
        "review_score": 9.393
      },
      {
        "room_type_id": 692303021,
        "name": "Phòng Đôi Phổ Thông (Economy Double Room)",
        "name_en": "(Economy Double Room)",
        "room_size": null,
        "size_sqm": null,
        "max_occupancy": null,
        "max_occupancy_text": null,
        "bed_type": "1 giường đôi lớn",
        "bed_types": [
          "1 giường đôi lớn"
        ],
        "room_view": null,
        "is_sold_out": false,
        "facilities": [],
        "room_amenities": [
          "1 giường đôi lớn",
          "Phòng tắm và vật dụng vệ sinh",
          "Tiện nghi",
          "phòng tắm riêng",
          "Điều hòa"
        ],
        "price": null,
        "image_count": 1,
        "images": [
          "https://q-xx.bstatic.com/xdata/images/hotel/840x460/103340832.jpg?k=7805f33c257ef971bc958aa8d8e7f9af8428159e410296b56ba946d0754d6dbe&o="
        ],
        "review_score": 9.6
      },
      {
        "room_type_id": 692303036,
        "name": "Phòng Tiêu Chuẩn Giường Đôi (Standard Double Room)",
        "name_en": "(Standard Double Room)",
        "room_size": null,
        "size_sqm": null,
        "max_occupancy": null,
        "max_occupancy_text": null,
        "bed_type": "1 giường đôi lớn",
        "bed_types": [
          "1 giường đôi lớn"
        ],
        "room_view": null,
        "is_sold_out": false,
        "facilities": [],
        "room_amenities": [
          "1 giường đôi lớn",
          "Phòng tắm và vật dụng vệ sinh",
          "Tiện nghi",
          "phòng tắm riêng",
          "Điều hòa"
        ],
        "price": null,
        "image_count": 1,
        "images": [
          "https://q-xx.bstatic.com/xdata/images/hotel/840x460/103340832.jpg?k=7805f33c257ef971bc958aa8d8e7f9af8428159e410296b56ba946d0754d6dbe&o="
        ],
        "review_score": 10.0
      }
    ]
  },
  "rooms": [
    {
      "room_type_id": 5692724,
      "name": "Phòng 4 Người (Quadruple Room)",
      "name_en": "(Quadruple Room)",
      "room_size": "30 m²",
      "size_sqm": 30.0,
      "max_occupancy": null,
      "max_occupancy_text": null,
      "bed_type": "2 giường lớn",
      "bed_types": [
        "2 giường lớn"
      ],
      "room_view": "Hướng Núi",
      "is_sold_out": false,
      "facilities": [
        "Hướng Núi",
        "Vòi sen",
        "Phòng tắm chung"
      ],
      "room_amenities": [
        "2 giường lớn",
        "30 m²",
        "Ban công/sân hiên",
        "Bàn trang điểm phù hợp cho người khuyết tật",
        "Bếp đầy đủ",
        "Bố trí và nội thất phòng",
        "Các loại khăn",
        "Cách âm",
        "Dép đi trong nhà",
        "Giá treo quần áo",
        "Giải trí ",
        "Hướng Núi",
        "Khu vực tiếp khách",
        "Khu vực ăn uống riêng",
        "Khả năng tiếp cận cho người khuyết tật",
        "Lối đi riêng",
        "Màn",
        "Nhà vệ sinh phụ",
        "Phòng tắm chung",
        "Phòng tắm phụ",
        "Phòng tắm và vật dụng vệ sinh",
        "Quạt",
        "Quần áo và Giặt ủi",
        "Sàn lát gạch/Sàn đá cẩm thạch",
        "Sản phẩm vệ sinh",
        "TV",
        "Thùng rác",
        "Tiện nghi",
        "Tiện nghi BBQ",
        "Truyền hình cáp/vệ tinh",
        "Tủ lạnh",
        "Vòi sen",
        "Vải trải giường",
        "Vật dụng tắm rửa",
        "phòng tắm riêng",
        "Ăn uống",
        "Điều hòa",
        "Đồ gỗ ngoài trời",
        "Ổ cắm điện gần giường"
      ],
      "price": null,
      "image_count": 1,
      "images": [
        "https://q-xx.bstatic.com/xdata/images/hotel/840x460/103340832.jpg?k=7805f33c257ef971bc958aa8d8e7f9af8428159e410296b56ba946d0754d6dbe&o="
      ],
      "review_score": 8.8
    },
    {
      "room_type_id": 692303030,
      "name": "Phòng Hạng Tiết kiệm Cho 4 Người (Economy Quadruple Room)",
      "name_en": "(Economy Quadruple Room)",
      "room_size": null,
      "size_sqm": null,
      "max_occupancy": null,
      "max_occupancy_text": null,
      "bed_type": "2 giường đôi lớn",
      "bed_types": [
        "2 giường đôi lớn"
      ],
      "room_view": null,
      "is_sold_out": false,
      "facilities": [],
      "room_amenities": [
        "2 giường đôi lớn",
        "Phòng tắm và vật dụng vệ sinh",
        "Tiện nghi",
        "phòng tắm riêng",
        "Điều hòa"
      ],
      "price": null,
      "image_count": 1,
      "images": [
        "https://q-xx.bstatic.com/xdata/images/hotel/840x460/103340832.jpg?k=7805f33c257ef971bc958aa8d8e7f9af8428159e410296b56ba946d0754d6dbe&o="
      ],
      "review_score": 10.0
    },
    {
      "room_type_id": 5692986,
      "name": "Phòng Đôi (Double Room)",
      "name_en": "(Double Room)",
      "room_size": "20 m²",
      "size_sqm": 20.0,
      "max_occupancy": null,
      "max_occupancy_text": null,
      "bed_type": "1 giường lớn",
      "bed_types": [
        "1 giường lớn"
      ],
      "room_view": "Hướng Núi",
      "is_sold_out": false,
      "facilities": [
        "Hướng Núi",
        "Vòi sen",
        "Phòng tắm chung"
      ],
      "room_amenities": [
        "1 giường lớn",
        "20 m²",
        "Ban công/sân hiên",
        "Bàn trang điểm phù hợp cho người khuyết tật",
        "Bếp đầy đủ",
        "Bố trí và nội thất phòng",
        "Các loại khăn",
        "Cách âm",
        "Dép đi trong nhà",
        "Giá treo quần áo",
        "Giải trí ",
        "Hướng Núi",
        "Khu vực tiếp khách",
        "Khu vực ăn uống riêng",
        "Khả năng tiếp cận cho người khuyết tật",
        "Lối đi riêng",
        "Màn",
        "Nhà vệ sinh phụ",
        "Phòng tắm chung",
        "Phòng tắm phụ",
        "Phòng tắm và vật dụng vệ sinh",
        "Quạt",
        "Quần áo và Giặt ủi",
        "Sàn lát gạch/Sàn đá cẩm thạch",
        "Sản phẩm vệ sinh",
        "TV",
        "Thùng rác",
        "Tiện nghi",
        "Tiện nghi BBQ",
        "Truyền hình cáp/vệ tinh",
        "Tủ lạnh",
        "Vòi sen",
        "Vải trải giường",
        "Vật dụng tắm rửa",
        "phòng tắm riêng",
        "Ăn uống",
        "Điều hòa",
        "Đồ gỗ ngoài trời",
        "Ổ cắm điện gần giường"
      ],
      "price": null,
      "image_count": 1,
      "images": [
        "https://q-xx.bstatic.com/xdata/images/hotel/840x460/103340832.jpg?k=7805f33c257ef971bc958aa8d8e7f9af8428159e410296b56ba946d0754d6dbe&o="
      ],
      "review_score": 9.393
    },
    {
      "room_type_id": 692303021,
      "name": "Phòng Đôi Phổ Thông (Economy Double Room)",
      "name_en": "(Economy Double Room)",
      "room_size": null,
      "size_sqm": null,
      "max_occupancy": null,
      "max_occupancy_text": null,
      "bed_type": "1 giường đôi lớn",
      "bed_types": [
        "1 giường đôi lớn"
      ],
      "room_view": null,
      "is_sold_out": false,
      "facilities": [],
      "room_amenities": [
        "1 giường đôi lớn",
        "Phòng tắm và vật dụng vệ sinh",
        "Tiện nghi",
        "phòng tắm riêng",
        "Điều hòa"
      ],
      "price": null,
      "image_count": 1,
      "images": [
        "https://q-xx.bstatic.com/xdata/images/hotel/840x460/103340832.jpg?k=7805f33c257ef971bc958aa8d8e7f9af8428159e410296b56ba946d0754d6dbe&o="
      ],
      "review_score": 9.6
    },
    {
      "room_type_id": 692303036,
      "name": "Phòng Tiêu Chuẩn Giường Đôi (Standard Double Room)",
      "name_en": "(Standard Double Room)",
      "room_size": null,
      "size_sqm": null,
      "max_occupancy": null,
      "max_occupancy_text": null,
      "bed_type": "1 giường đôi lớn",
      "bed_types": [
        "1 giường đôi lớn"
      ],
      "room_view": null,
      "is_sold_out": false,
      "facilities": [],
      "room_amenities": [
        "1 giường đôi lớn",
        "Phòng tắm và vật dụng vệ sinh",
        "Tiện nghi",
        "phòng tắm riêng",
        "Điều hòa"
      ],
      "price": null,
      "image_count": 1,
      "images": [
        "https://q-xx.bstatic.com/xdata/images/hotel/840x460/103340832.jpg?k=7805f33c257ef971bc958aa8d8e7f9af8428159e410296b56ba946d0754d6dbe&o="
      ],
      "review_score": 10.0
    }
  ],
  "reviews_detail": {
    "score": 9.2,
    "score_text": "Trên cả tuyệt vời",
    "review_count": 283,
    "comments_count": 449,
    "grades": [
      {
        "name": "Dịch vụ",
        "score": 9.6
      },
      {
        "name": "Đáng tiền",
        "score": 9.4
      },
      {
        "name": "Vị trí",
        "score": 9.3
      },
      {
        "name": "",
        "score": 9.2
      },
      {
        "name": "Độ sạch sẽ",
        "score": 9.2
      },
      {
        "name": "Sự thoải mái và chất lượng phòng",
        "score": 9.1
      },
      {
        "name": "Cơ sở vật chất",
        "score": 8.7
      }
    ],
    "tags": [
      {
        "tag": "Địa điểm",
        "mentioned": 7,
        "positive_pct": 100.0
      },
      {
        "tag": "Chủ nhà",
        "mentioned": 6,
        "positive_pct": 100.0
      },
      {
        "tag": "Bãi biển",
        "mentioned": 5,
        "positive_pct": 100.0
      },
      {
        "tag": "Độ sạch sẽ",
        "mentioned": 3,
        "positive_pct": 100.0
      },
      {
        "tag": "Tiện nghi trong phòng",
        "mentioned": 2,
        "positive_pct": 50.0
      },
      {
        "tag": "Dịch vụ",
        "mentioned": 2,
        "positive_pct": 100.0
      },
      {
        "tag": "Phòng tắm",
        "mentioned": 1,
        "positive_pct": 100.0
      },
      {
        "tag": "Bữa tối",
        "mentioned": 1,
        "positive_pct": 100.0
      },
      {
        "tag": "Gia đình",
        "mentioned": 1,
        "positive_pct": 100.0
      },
      {
        "tag": "Bữa sáng",
        "mentioned": 1,
        "positive_pct": 0.0
      },
      {
        "tag": "Không khí",
        "mentioned": 1,
        "positive_pct": 100.0
      },
      {
        "tag": "Điều hòa",
        "mentioned": 1,
        "positive_pct": 100.0
      },
      {
        "tag": "Kích thước phòng",
        "mentioned": 1,
        "positive_pct": 0.0
      },
      {
        "tag": "Vòi sen",
        "mentioned": 1,
        "positive_pct": 100.0
      },
      {
        "tag": "Thiết kế phòng",
        "mentioned": 1,
        "positive_pct": 100.0
      },
      {
        "tag": "Thiên nhiên",
        "mentioned": 1,
        "positive_pct": 100.0
      }
    ],
    "word_cloud": [],
    "demographics": [
      {
        "name": "Khách đi công tác",
        "count": 1,
        "score": 10.0
      },
      {
        "name": "Cặp đôi",
        "count": 30,
        "score": 9.2
      },
      {
        "name": "Khách du lịch một mình",
        "count": 19,
        "score": 9.4
      },
      {
        "name": "Gia đình có trẻ nhỏ",
        "count": 8,
        "score": 8.9
      },
      {
        "name": "Gia đình có thanh thiếu niên",
        "count": 5,
        "score": 9.1
      },
      {
        "name": "Nhóm du khách",
        "count": 10,
        "score": 8.9
      },
      {
        "name": "Cặp đôi",
        "count": 78,
        "score": 9.2
      },
      {
        "name": "Khách du lịch một mình",
        "count": 65,
        "score": 9.2
      },
      {
        "name": "Gia đình có trẻ nhỏ",
        "count": 34,
        "score": 9.5
      },
      {
        "name": "Nhóm du khách",
        "count": 26,
        "score": 9.7
      }
    ],
    "sample_comments": [
      {
        "rating": 10.0,
        "rating_text": "Trên cả tuyệt vời",
        "date": "11 tháng 5 2026",
        "check_in": "Tháng 5 năm 2026",
        "text": "Cô chủ rất nhiệt tình và mến khách, không gian rất ấm cúng gần gũi, con đường trước homestay rất đẹp.",
        "title": "Home rất hợp với solo trip",
        "positives": "",
        "negatives": "",
        "response": null,
        "reviewer_name": "Ngan",
        "reviewer_type": "Du lịch một mình",
        "reviewer_country": "Việt Nam",
        "room_type": "Phòng Đôi"
      },
      {
        "rating": 9.0,
        "rating_text": "Trên cả tuyệt vời",
        "date": "06 tháng 8 2025",
        "check_in": "",
        "text": "",
        "title": "Tuyệt vời",
        "positives": "Chủ quán nấu ăn ngon, nhiệt tình hỗ trợ khách",
        "negatives": "Cạnh cửa sổ có phế liệu",
        "response": null,
        "reviewer_name": "Le",
        "reviewer_type": "Du lịch một mình",
        "reviewer_country": "",
        "room_type": ""
      },
      {
        "rating": 10.0,
        "rating_text": "Trên cả tuyệt vời",
        "date": "02 tháng 4 2026",
        "check_in": "Tháng 3 năm 2026",
        "text": "Vị trí homestay gần biển, bãi biển sạch và đẹp chỉ cách 5 phút đi bộ\nTôi sẽ quay lại nơi này",
        "title": "Chủ nhà rất thân thiện ",
        "positives": "",
        "negatives": "",
        "response": null,
        "reviewer_name": "Minh",
        "reviewer_type": "Du lịch một mình",
        "reviewer_country": "Việt Nam",
        "room_type": "Phòng Đôi"
      },
      {
        "rating": 7.0,
        "rating_text": "Rất tốt",
        "date": "01 tháng 3 2025",
        "check_in": "",
        "text": "",
        "title": "Rất tốt",
        "positives": "Cô chú dễ thương",
        "negatives": "",
        "response": null,
        "reviewer_name": "Quỳnh",
        "reviewer_type": "Đi công tác",
        "reviewer_country": "",
        "room_type": ""
      },
      {
        "rating": 10.0,
        "rating_text": "Trên cả tuyệt vời",
        "date": "23 tháng 3 2026",
        "check_in": "Tháng 3 năm 2026",
        "text": "Kỳ nghỉ tuyệt vời tại homestay này!\nChúng tôi đã có thể thuê xe máy cũng như mặt nạ và ống thở để khám phá đảo, điều này giúp chuyến đi của chúng tôi trở nên dễ dàng và thú vị.\n\nChủ nhà đã cho chúng tôi những gợi ý địa phương tuyệt vời, và sự chào đón rất ấm áp, với đồ ăn và đồ uống được cung cấp khi đến nơi.\n\nTôi chắc chắn giới thiệu nơi này!",
        "title": "Vị trí tuyệt vời và tiện nghi",
        "positives": "",
        "negatives": "",
        "response": null,
        "reviewer_name": "Soline",
        "reviewer_type": "Gia đình có trẻ em",
        "reviewer_country": "Pháp",
        "room_type": "Phòng Hạng Tiết kiệm Cho 4 Người"
      },
      {
        "rating": 10.0,
        "rating_text": "Trên cả tuyệt vời",
        "date": "29 tháng 4 2024",
        "check_in": "",
        "text": "",
        "title": "Trên cả tuyệt vời",
        "positives": "Vị trí gần bãi tắm, gần khu trung tâm để đi chơi và mua sắm nhưng rất mát mẻ và yên tĩnh. Chị chủ homestay cực kỳ thân thiện, tốt bụng. Giá cả rất rẻ và hợp lý",
        "negatives": "",
        "response": null,
        "reviewer_name": "Nhung",
        "reviewer_type": "Đi công tác",
        "reviewer_country": "",
        "room_type": ""
      },
      {
        "rating": 10.0,
        "rating_text": "Trên cả tuyệt vời",
        "date": "21 tháng 4 2026",
        "check_in": "Tháng 2 năm 2026",
        "text": "Yêu nơi này. Nó cảm giác như là một phần của một gia đình tốt đẹp.",
        "title": "Địa điểm yên tĩnh và chủ nhà xinh đẹp",
        "positives": "",
        "negatives": "",
        "response": null,
        "reviewer_name": "Ngoc",
        "reviewer_type": "Du lịch một mình",
        "reviewer_country": "Việt Nam",
        "room_type": "Phòng Đôi"
      },
      {
        "rating": 10.0,
        "rating_text": "Trên cả tuyệt vời",
        "date": "18 tháng 7 2023",
        "check_in": "",
        "text": "",
        "title": "Trên cả tuyệt vời",
        "positives": "Chủ nhà dễ thương",
        "negatives": "Đồ ăn ngon",
        "response": null,
        "reviewer_name": "Thị",
        "reviewer_type": "Cặp đôi",
        "reviewer_country": "",
        "room_type": ""
      },
      {
        "rating": 10.0,
        "rating_text": "Trên cả tuyệt vời",
        "date": "10 tháng 8 2025",
        "check_in": "Tháng 8 năm 2025",
        "text": "Mọi người đến chỉ để ở lại một đêm đã quyết định ở lại lâu hơn, tóm tắt một cách hoàn hảo.",
        "title": "chuyến đi đến hòn đảo hoàn hảo",
        "positives": "",
        "negatives": "",
        "response": null,
        "reviewer_name": "Artur",
        "reviewer_type": "Du lịch một mình",
        "reviewer_country": "Ba Lan",
        "room_type": "Phòng Đôi"
      },
      {
        "rating": 6.0,
        "rating_text": "Hài Lòng",
        "date": "01 tháng 5 2026",
        "check_in": "",
        "text": "",
        "title": "While we enjoyed Chàm Island and our stay with this lovely family, the poor bed and wifi disappointe",
        "positives": "The family who ran the Homestay were kind, generous and helpful. The mom made us a lovely lunch free of charge, and they always had their special island tea ready for us to drink. The location was good…close to restaurants and the harbour village one way, and to a nice swimming beach in the other direction.",
        "negatives": "The bed was very hard and uncomfortable. The wifi was unusable in the room.",
        "response": null,
        "reviewer_name": "Julie",
        "reviewer_type": "Cặp đôi",
        "reviewer_country": "",
        "room_type": ""
      }
    ]
  },
  "rating_overall": 9.2,
  "rating_count": 283,
  "rating_breakdown": {
    "Dịch vụ": 9.6,
    "Đáng tiền": 9.4,
    "Vị trí": 9.3,
    "Độ sạch sẽ": 9.2,
    "Sự thoải mái và chất lượng phòng": 9.1,
    "Cơ sở vật chất": 8.7
  },
  "secondary": {
    "description_full": "Với Bãi Ông nằm cách đó 2 phút đi bộ, Trang Vu Homestay Cu Lao Cham cung cấp chỗ nghỉ, nhà hàng, khu vườn, phòng chờ chung và sân hiên. WiFi và chỗ đậu xe riêng đều có sẵn tại homestay miễn phí.\n\nMột số căn có TV truyền hình cáp, bếp đầy đủ tiện nghi với tủ lạnh, cùng phòng tắm riêng được trang bị vòi sen và đồ vệ sinh cá nhân miễn phí.\n\nTrang Vu Homestay Cu Lao Cham cách Cù Lao Chàm 3.2 km.",
    "hotel_policy": {
      "extrabedPolicies": [
        {
          "type": 1,
          "description": "Giường phụ tùy thuộc vào loại phòng bạn chọn, xin vui lòng kiểm tra thông tin phòng để biết thêm chi tiết."
        }
      ],
      "policyNotes": [],
      "hideAutomatedChildPolicyText": false,
      "extraBedAge": 1,
      "hasBcomChildPolicy": false
    },
    "other_policies": [],
    "dateless_rooms_count": 5,
    "dateless_rooms": [
      {
        "room_id": 5692724,
        "name": "Phòng 4 Người (Quadruple Room)",
        "features": [],
        "image_count": 1,
        "bed_summary": {
          "symbol": "ficon-bed",
          "title": "2 giường lớn",
          "isAvailable": true,
          "id": 15,
          "value": 0.0,
          "associatedFilters": [
            "twin-bed",
            "double-bed"
          ],
          "targetType": 0,
          "hasDescription": false
        }
      },
      {
        "room_id": 5692986,
        "name": "Phòng Đôi (Double Room)",
        "features": [],
        "image_count": 1,
        "bed_summary": {
          "symbol": "ficon-bed",
          "title": "1 giường lớn",
          "isAvailable": true,
          "id": 15,
          "value": 0.0,
          "associatedFilters": [
            "twin-bed",
            "double-bed"
          ],
          "targetType": 0,
          "hasDescription": false
        }
      },
      {
        "room_id": 692303030,
        "name": "Phòng Hạng Tiết kiệm Cho 4 Người (Economy Quadruple Room)",
        "features": [],
        "image_count": 1,
        "bed_summary": {
          "symbol": "ficon-bed",
          "title": "2 giường đôi lớn",
          "isAvailable": true,
          "id": 15,
          "value": 0.0,
          "associatedFilters": [
            "twin-bed",
            "double-bed"
          ],
          "targetType": 0,
          "hasDescription": false
        }
      },
      {
        "room_id": 692303021,
        "name": "Phòng Đôi Phổ Thông (Economy Double Room)",
        "features": [],
        "image_count": 1,
        "bed_summary": {
          "symbol": "ficon-bed",
          "title": "1 giường đôi lớn",
          "isAvailable": true,
          "id": 15,
          "value": 0.0,
          "associatedFilters": [
            "twin-bed",
            "double-bed"
          ],
          "targetType": 0,
          "hasDescription": false
        }
      },
      {
        "room_id": 692303036,
        "name": "Phòng Tiêu Chuẩn Giường Đôi (Standard Double Room)",
        "features": [],
        "image_count": 1,
        "bed_summary": {
          "symbol": "ficon-bed",
          "title": "1 giường đôi lớn",
          "isAvailable": true,
          "id": 15,
          "value": 0.0,
          "associatedFilters": [
            "twin-bed",
            "double-bed"
          ],
          "targetType": 0,
          "hasDescription": false
        }
      }
    ]
  },
  "description_short": "Nằm ở vị trí trung tâm tại Tam Hiệp của Tân Hiệp, chỗ nghỉ này đặt quý khách ở gần các điểm thu hút và tùy chọn ăn uống thú vị.",
  "faq": [
    {
      "question": "Có các hoạt động thể thao dưới nước nào tại Trang Vu Homestay Cu Lao Cham?",
      "answer": "Trang Vu Homestay Cu Lao Cham có nhiều hoạt động thể thao dưới nước như xuồng, lặn biển với bình khí, câu cá và bơi với ống thở để quý khách có thể trải nghiệm trong thời gian ở tại đây.",
      "category": "property_faq_hotel_facilities_things-to-do"
    },
    {
      "question": "Trang Vu Homestay Cu Lao Cham có dịch vụ giặt là không?",
      "answer": "Có! Trang Vu Homestay Cu Lao Cham cung cấp dịch vụ giặt là để quý khách sử dụng bất cứ khi nào cần quần áo mới sạch thơm trong suốt kỳ nghỉ của mình. Vui lòng liên hệ với cơ sở lưu trú để biết thêm thông tin.",
      "category": "property_faq_hotel_facilities_cleaning"
    },
    {
      "question": "Trang Vu Homestay Cu Lao Cham có bãi đỗ xe không?",
      "answer": "Trang Vu Homestay Cu Lao Cham có bãi đỗ xe miễn phí cho mọi khách đến cơ sở lưu trú bằng phương tiện riêng. Vui lòng liên hệ với cơ sở lưu trú để biết thêm thông tin hoặc đăng nhập vào tài khoản Agoda và liên hệ với cơ sở lưu trú thông qua hộp trò chuyện nhắn tin trực tiếp của Agoda.",
      "category": "property_faq_hotel_facilities_parking"
    },
    {
      "question": "Điều gì ở Trang Vu Homestay Cu Lao Cham được khách yêu thích nhất?",
      "answer": "Khách đã xác thực lưu trú tại Trang Vu Homestay Cu Lao Cham đã đánh giá 9.472 cho cơ sở lưu trú này vì service hiếm có như là điểm nhấn chính cho kỳ lưu trú của họ.",
      "category": "property_faq_review_topic"
    },
    {
      "question": "Mức độ hài lòng trong bài đánh giá của khách về hướng phòng của Trang Vu Homestay Cu Lao Cham?",
      "answer": "100.0% bài đánh giá từ khách đã xác thực đã đưa ra nhận xét và phản hồi tích cực về hướng phòng tại cơ sở lưu trú này. Quý khách có thể xem các đánh giá chi tiết hơn của khách hàng và nhận xét về Trang Vu Homestay Cu Lao Cham ở phần đánh giá.",
      "category": "property_faq_review_topic"
    },
    {
      "question": "Mức độ hài lòng trong bài đánh giá của khách về cà phê tại Trang Vu Homestay Cu Lao Cham?",
      "answer": "100.0% bài đánh giá từ khách đã xác thực đã đưa ra nhận xét và phản hồi tích cực về cà phê tại cơ sở lưu trú này. Quý khách có thể xem các đánh giá chi tiết hơn của khách hàng và nhận xét về Trang Vu Homestay Cu Lao Cham ở phần đánh giá.",
      "category": "property_faq_review_topic"
    },
    {
      "question": "Điểm trung bình từ khách gia đình có trẻ nhỏ dành cho Trang Vu Homestay Cu Lao Cham",
      "answer": "8.7 là điểm số trung bình của khách gia đình có trẻ nhỏ đã xác thực nghỉ tại Trang Vu Homestay Cu Lao Cham đánh giá cơ sở lưu trú này. Quý khách có thể xem các đánh giá chi tiết hơn của khách hàng và nhận xét bằng cách lọc theo đối tượng khách đã được xác thực ở phần đánh giá.",
      "category": "property_faq_review_traveler_type"
    },
    {
      "question": "Điểm trung bình từ khách gia đình có trẻ lớn dành cho Trang Vu Homestay Cu Lao Cham",
      "answer": "9.1 là điểm số trung bình của khách gia đình có trẻ lớn đã xác thực nghỉ tại Trang Vu Homestay Cu Lao Cham đánh giá cơ sở lưu trú này. Quý khách có thể xem các đánh giá chi tiết hơn của khách hàng và nhận xét bằng cách lọc theo đối tượng khách đã được xác thực ở phần đánh giá.",
      "category": "property_faq_review_traveler_type"
    },
    {
      "question": "Điểm trung bình từ khách đi theo nhóm dành cho Trang Vu Homestay Cu Lao Cham",
      "answer": "8.8 là điểm số trung bình của khách đi theo nhóm trước đây đã nghỉ tại Trang Vu Homestay Cu Lao Cham đánh giá cơ sở lưu trú này. Quý khách có thể xem các đánh giá chi tiết hơn của khách hàng và nhận xét bằng cách lọc theo đối tượng khách đã được xác thực ở phần đánh giá.",
      "category": "property_faq_review_traveler_type"
    },
    {
      "question": "Du khách nội địa nghĩ gì về Trang Vu Homestay Cu Lao Cham?",
      "answer": "Du khách nội địa đã từng ở tại Trang Vu Homestay Cu Lao Cham đánh giá trung bình 9.7 cho cơ sở lưu trú này. Quý khách có thể xem các đánh giá chi tiết hơn của khách hàng và nhận xét về cơ sở lưu trú này ở phần đánh giá.",
      "category": "property_faq_review_traveler_type"
    }
  ],
  "suitable_for": [
    "Khách đi công tác",
    "Cặp đôi",
    "Khách du lịch một mình",
    "Gia đình có trẻ nhỏ",
    "Gia đình có thanh thiếu niên",
    "Nhóm du khách"
  ],
  "view_types": [
    "Hướng Núi"
  ],
  "tags": [
    "Chất lượng và tiện nghi phòng tuyệt vời",
    "Cặp đôi",
    "Dịch vụ chăm sóc khách chuyên nghiệp",
    "Gia đình có thanh thiếu niên",
    "Gia đình có trẻ nhỏ",
    "Hướng Núi",
    "Khách du lịch một mình",
    "Khách đi công tác",
    "Nhân viên chăm sóc khách hàng",
    "Nhóm du khách",
    "Nhận/trả phòng [nhanh]",
    "Rất sạch sẽ",
    "Thích hợp cho các hoạt động",
    "Vườn",
    "Wi-Fi miễn phí trong tất cả các phòng!",
    "Điều hòa",
    "Đáng tiền nhất"
  ],
  "embedding_text": "Trang Vu Homestay Cu Lao Cham - khách sạn 4.0 sao tại Tân Hiệp.\nĐịa chỉ: BÃI ÔNG, CÙ LAO CHÀM, Tam Hiệp, Tân Hiệp, Việt Nam.\nNằm ở vị trí trung tâm tại Tam Hiệp của Tân Hiệp, chỗ nghỉ này đặt quý khách ở gần các điểm thu hút và tùy chọn ăn uống thú vị.\nTiện ích: Bãi đỗ xe [miễn phí], Bơi với ống thở, Bơi xuồng, Bếp chung, Bữa ăn cho trẻ, Câu cá, Có cung cấp hóa đơn, Dịch vụ Internet, Dịch vụ giặt là, Dịch vụ phòng, Dịch vụ thanh toán không sử dụng tiền mặt, Dịch vụ đưa đón, Giữ hành lý, Internet, Không có văn phòng phẩm dùng chung, Lặn, Máy điều hòa ở khu vực chung, Nhà hàng, Nhân viên chăm sóc khách hàng, Nhân viên được đào tạo về giao thức an toàn, Nhận/trả phòng [nhanh], Nhận/trả phòng [riêng], Phòng chờ chung/khu vực TV, Phòng gia đình, Phòng không hút thuốc, Sân hiên, Thích hợp cho gia đình/trẻ em, Tiếng Anh, Vườn, Wi-Fi miễn phí trong tất cả các phòng!.\nĐiểm đánh giá 9.2/10 dựa trên 283 đánh giá.\nKhách hay nhắc đến: Địa điểm, Chủ nhà, Bãi biển, Độ sạch sẽ, Tiện nghi trong phòng, Dịch vụ, Phòng tắm, Bữa tối.\nCác loại phòng: Phòng 4 Người (Quadruple Room); Phòng Hạng Tiết kiệm Cho 4 Người (Economy Quadruple Room); Phòng Đôi (Double Room); Phòng Đôi Phổ Thông (Economy Double Room); Phòng Tiêu Chuẩn Giường Đôi (Standard Double Room).\nGần: Cù Lao Chàm, Cù Lao Chàm, Hòn Tai, Sân bay Quốc tế Đà Nẵng, Sân bay Chu Lai, Sân bay Quốc tế Phú Bài.",
  "_sources_captured": [
    "details",
    "faq",
    "reviews",
    "rooms",
    "secondary"
  ]
}